{"b4w_format_version": "6.02", "b4w_filepath_blend": "../../../blender/materials/ramps.blend", "actions": [], "images": [{"name": "noise_group_1.png", "uuid": "1f8946e4f845083336387270970d20f8", "filepath": "noise_group_1.png", "size": [256, 256], "source": "FILE", "colorspace_settings_name": "sRGB"}, {"name": "ao_dirt_worn_masks.png", "uuid": "3b055b0eecd39258c6568d7436eb96d5", "filepath": "../material_library/textures/ao_dirt_worn_masks.png", "size": [1024, 1024], "source": "FILE", "colorspace_settings_name": "sRGB"}, {"name": "gridline", "uuid": "9bafffb55b3de9219382c06d7e7160bb", "filepath": "../material_library/textures/gridline.png", "size": [512, 512], "source": "FILE", "colorspace_settings_name": "sRGB"}], "textures": [{"name": "FloorsCheckerboard0025_1_S", "uuid": "34a75ff5a830138d8f2cbc4ea8327541", "type": "IMAGE", "b4w_source_type": "NONE", "b4w_source_id": "", "b4w_source_size": "128", "b4w_enable_canvas_mipmapping": true, "extension": "REPEAT", "b4w_use_map_parallax": false, "b4w_parallax_scale": 0.02, "b4w_parallax_steps": 5, "b4w_parallax_lod_dist": 5, "b4w_water_foam": false, "b4w_foam_uv_freq": [1, 1], "b4w_foam_uv_magnitude": [1, 1], "b4w_shore_dist_map": false, "b4w_anisotropic_filtering": "DEFAULT", "b4w_shore_boundings": [0, 0, 0, 0], "b4w_max_shore_dist": 100, "b4w_disable_compression": true, "b4w_use_as_skydome": true, "b4w_use_as_environment_lighting": false, "image": {"uuid": "1f8946e4f845083336387270970d20f8"}, "frame_duration": 0, "frame_offset": 0, "frame_start": 0, "use_auto_refresh": false, "use_cyclic": false, "movie_length": 0, "b4w_nla_video": false, "noise_intensity": null, "noise_scale": null, "use_color_ramp": false, "color_ramp": null}, {"name": "ao_dirt_worn_masks", "uuid": "e6511b8e83573ef387fa450e2da041b8", "type": "IMAGE", "b4w_source_type": "NONE", "b4w_source_id": "", "b4w_source_size": "128", "b4w_enable_canvas_mipmapping": true, "extension": "REPEAT", "b4w_use_map_parallax": false, "b4w_parallax_scale": 0.02, "b4w_parallax_steps": 5, "b4w_parallax_lod_dist": 5, "b4w_water_foam": false, "b4w_foam_uv_freq": [1, 1], "b4w_foam_uv_magnitude": [1, 1], "b4w_shore_dist_map": false, "b4w_anisotropic_filtering": "DEFAULT", "b4w_shore_boundings": [0, 0, 0, 0], "b4w_max_shore_dist": 100, "b4w_disable_compression": false, "b4w_use_as_skydome": true, "b4w_use_as_environment_lighting": false, "image": {"uuid": "3b055b0eecd39258c6568d7436eb96d5"}, "frame_duration": 0, "frame_offset": 0, "frame_start": 0, "use_auto_refresh": false, "use_cyclic": false, "movie_length": 0, "b4w_nla_video": false, "noise_intensity": null, "noise_scale": null, "use_color_ramp": false, "color_ramp": null}, {"name": "gridline", "uuid": "fee7ebc79a9914564b68b3d957ad6b94", "type": "IMAGE", "b4w_source_type": "NONE", "b4w_source_id": "", "b4w_source_size": "128", "b4w_enable_canvas_mipmapping": true, "extension": "REPEAT", "b4w_use_map_parallax": false, "b4w_parallax_scale": 0.02, "b4w_parallax_steps": 5, "b4w_parallax_lod_dist": 5, "b4w_water_foam": false, "b4w_foam_uv_freq": [1, 1], "b4w_foam_uv_magnitude": [1, 1], "b4w_shore_dist_map": false, "b4w_anisotropic_filtering": "DEFAULT", "b4w_shore_boundings": [0, 0, 0, 0], "b4w_max_shore_dist": 100, "b4w_disable_compression": false, "b4w_use_as_skydome": true, "b4w_use_as_environment_lighting": false, "image": {"uuid": "9bafffb55b3de9219382c06d7e7160bb"}, "frame_duration": 0, "frame_offset": 0, "frame_start": 0, "use_auto_refresh": false, "use_cyclic": false, "movie_length": 0, "b4w_nla_video": false, "noise_intensity": null, "noise_scale": null, "use_color_ramp": false, "color_ramp": null}], "materials": [{"use_orco_tex_coord": false, "name": "ramp_texture", "use_nodes": true, "diffuse_color": [0.8, 0.8, 0.8], "diffuse_shader": "LAMBERT", "roughness": 0.5, "diffuse_fresnel": 0.1, "diffuse_fresnel_factor": 0.5, "darkness": 1, "diffuse_toon_size": 0.5, "diffuse_toon_smooth": 0.1, "diffuse_intensity": 0.8, "alpha": 1, "specular_alpha": 1, "raytrace_transparency": {"fresnel": 0, "fresnel_factor": 1.25}, "raytrace_mirror": {"reflect_factor": 0, "fresnel": 0, "fresnel_factor": 1.25}, "specular_color": [1, 1, 1], "specular_intensity": 0.5, "specular_shader": "COOKTORR", "specular_hardness": 50, "specular_ior": 4, "specular_slope": 0.1, "specular_toon_size": 0.5, "specular_toon_smooth": 0.1, "emit": 0, "ambient": 1, "use_vertex_color_paint": false, "b4w_water": false, "b4w_water_shore_smoothing": true, "b4w_water_absorb_factor": 6, "b4w_water_dynamic": false, "b4w_waves_height": 1, "b4w_waves_length": 10, "b4w_generated_mesh": false, "b4w_water_num_cascads": 5, "b4w_water_subdivs": 64, "b4w_water_detailed_dist": 1000, "b4w_water_fog_color": [0.4, 0.6, 0.7], "b4w_water_fog_density": 0.06, "b4w_foam_factor": 0.5, "b4w_shallow_water_col": [0, 0.8, 0.3], "b4w_shore_water_col": [0, 0.9, 0.2], "b4w_shallow_water_col_fac": 1, "b4w_shore_water_col_fac": 0.5, "b4w_water_dst_noise_scale0": 0.05, "b4w_water_dst_noise_scale1": 0.03, "b4w_water_dst_noise_freq0": 1.3, "b4w_water_dst_noise_freq1": 1, "b4w_water_dir_min_shore_fac": 0.4, "b4w_water_dir_freq": 0.5, "b4w_water_dir_noise_scale": 0.05, "b4w_water_dir_noise_freq": 0.07, "b4w_water_dir_min_noise_fac": 0.5, "b4w_water_dst_min_fac": 0.2, "b4w_water_waves_hor_fac": 5, "b4w_water_sss_strength": 1, "b4w_water_sss_width": 0.45, "b4w_water_norm_uv_velocity": 0.05, "b4w_water_enable_caust": false, "b4w_water_caust_scale": 0.25, "b4w_water_caust_brightness": 0.5, "b4w_terrain": false, "b4w_dynamic_grass_size": "", "b4w_dynamic_grass_color": "", "b4w_do_not_render": false, "b4w_lens_flares": false, "b4w_collision": false, "b4w_use_ghost": false, "b4w_collision_id": "", "b4w_collision_margin": 0.03999999910593033, "b4w_collision_group": 128, "b4w_collision_mask": 65407, "b4w_double_sided_lighting": false, "b4w_wettable": false, "b4w_refractive": false, "b4w_refr_bump": 0.0010000000474974513, "b4w_render_above_all": false, "physics": {"friction": 0.5, "elasticity": 0}, "type": "SURFACE", "b4w_halo_sky_stars": false, "b4w_halo_stars_blend_height": 10.0, "b4w_halo_stars_min_height": 0.0, "halo": {"hardness": 50, "size": 0.5, "b4w_halo_rings_color": [1, 1, 1], "b4w_halo_lines_color": [1, 1, 1], "ring_count": 0, "line_count": 0, "star_tip_count": 0}, "use_transparency": false, "use_shadeless": false, "use_tangent_shading": false, "pass_index": 0, "offset_z": 0, "game_settings": {"alpha_blend": "OPAQUE", "use_backface_culling": true}, "uv_vc_key": "UVMapUVMap", "node_tree": {"nodes": [{"name": "Math.013", "type": "MATH", "operation": "MULTIPLY", "use_clamp": false, "inputs": [{"name": "Value", "identifier": "Value", "is_linked": true, "default_value": 0.5}, {"name": "Value", "identifier": "Value_001", "is_linked": false, "default_value": 4}], "outputs": [{"name": "Value", "identifier": "Value", "is_linked": true, "default_value": 0}]}, {"name": "ColorRamp", "type": "VALTORGB", "color_ramp": {"elements": [{"position": 0.043, "color": [1, 0, 0, 1]}, {"position": 0.286, "color": [0, 1, 0, 1]}, {"position": 0.62, "color": [1, 0, 0, 1]}, {"position": 0.936, "color": [0, 0, 1, 1]}], "interpolation": "LINEAR"}, "inputs": [{"name": "Fac", "identifier": "Fac", "is_linked": true, "default_value": 0.5}], "outputs": [{"name": "Color", "identifier": "Color", "is_linked": true, "default_value": [0, 0, 0, 0]}, {"name": "Alpha", "identifier": "Alpha", "is_linked": false, "default_value": 0}]}, {"name": "Texture", "type": "TEXTURE", "texture": {"uuid": "34a75ff5a830138d8f2cbc4ea8327541"}, "inputs": [{"name": "Vector", "identifier": "Vector", "is_linked": true, "default_value": [0, 0, 0]}], "outputs": [{"name": "Value", "identifier": "Value", "is_linked": false, "default_value": 0}, {"name": "Color", "identifier": "Color", "is_linked": true, "default_value": [0, 0, 0, 0]}, {"name": "Normal", "identifier": "Normal", "is_linked": false, "default_value": [0, 0, 0]}]}, {"name": "Separate RGB", "type": "SEPRGB", "inputs": [{"name": "Image", "identifier": "Image", "is_linked": true, "default_value": [0.8, 0.8, 0.8, 1]}], "outputs": [{"name": "R", "identifier": "R", "is_linked": false, "default_value": 0}, {"name": "G", "identifier": "G", "is_linked": true, "default_value": 0}, {"name": "B", "identifier": "B", "is_linked": false, "default_value": 0}]}, {"name": "Geometry", "type": "GEOMETRY", "uv_layer": "UVMap", "color_layer": "", "inputs": [], "outputs": [{"name": "Global", "identifier": "Global", "is_linked": false, "default_value": [0, 0, 0]}, {"name": "Local", "identifier": "Local", "is_linked": false, "default_value": [0, 0, 0]}, {"name": "View", "identifier": "View", "is_linked": false, "default_value": [0, 0, 0]}, {"name": "Orco", "identifier": "Orco", "is_linked": false, "default_value": [0, 0, 0]}, {"name": "UV", "identifier": "UV", "is_linked": true, "default_value": [0, 0, 0]}, {"name": "Normal", "identifier": "Normal", "is_linked": false, "default_value": [0, 0, 0]}, {"name": "Vertex Color", "identifier": "Vertex Color", "is_linked": false, "default_value": [0, 0, 0, 0]}, {"name": "Vertex Alpha", "identifier": "Vertex Alpha", "is_linked": false, "default_value": 0}, {"name": "Front/Back", "identifier": "Front/Back", "is_linked": false, "default_value": 0}]}, {"name": "Math.012", "type": "MATH", "operation": "ADD", "use_clamp": false, "inputs": [{"name": "Value", "identifier": "Value", "is_linked": true, "default_value": 0.5}, {"name": "Value", "identifier": "Value_001", "is_linked": false, "default_value": -0.11}], "outputs": [{"name": "Value", "identifier": "Value", "is_linked": true, "default_value": 0}]}, {"name": "Output.001", "type": "OUTPUT", "inputs": [{"name": "Color", "identifier": "Color", "is_linked": true, "default_value": [0, 0, 0, 1]}, {"name": "Alpha", "identifier": "Alpha", "is_linked": false, "default_value": 1}], "outputs": []}, {"name": "Mapping", "type": "MAPPING", "translation": [0, 0, 0], "rotation": [0, 0, 0], "scale": [5, 5, 1], "vector_type": "POINT", "use_min": false, "use_max": false, "min": [0, 0, 0], "max": [1, 1, 1], "inputs": [{"name": "Vector", "identifier": "Vector", "is_linked": true, "default_value": [0, 0, 0]}], "outputs": [{"name": "Vector", "identifier": "Vector", "is_linked": true, "default_value": [0, 0, 0]}]}], "links": [{"from_node": {"name": "Mapping"}, "to_node": {"name": "Texture"}, "from_socket": {"identifier": "Vector"}, "to_socket": {"identifier": "Vector"}}, {"from_node": {"name": "Geometry"}, "to_node": {"name": "Mapping"}, "from_socket": {"identifier": "UV"}, "to_socket": {"identifier": "Vector"}}, {"from_node": {"name": "Texture"}, "to_node": {"name": "Separate RGB"}, "from_socket": {"identifier": "Color"}, "to_socket": {"identifier": "Image"}}, {"from_node": {"name": "Math.012"}, "to_node": {"name": "Math.013"}, "from_socket": {"identifier": "Value"}, "to_socket": {"identifier": "Value"}}, {"from_node": {"name": "Separate RGB"}, "to_node": {"name": "Math.012"}, "from_socket": {"identifier": "G"}, "to_socket": {"identifier": "Value"}}, {"from_node": {"name": "Math.013"}, "to_node": {"name": "ColorRamp"}, "from_socket": {"identifier": "Value"}, "to_socket": {"identifier": "Fac"}}, {"from_node": {"name": "ColorRamp"}, "to_node": {"name": "Output.001"}, "from_socket": {"identifier": "Color"}, "to_socket": {"identifier": "Color"}}], "animation_data": null}, "texture_slots": [], "uuid": "f0ea9c86d107f8dd6caf0704c1e3c8d6", "source_uuid": "67f0dd8835265d35d9c73cef9035e5de"}, {"use_orco_tex_coord": false, "name": "constant_material", "use_nodes": true, "diffuse_color": [0.8, 0.8, 0.8], "diffuse_shader": "LAMBERT", "roughness": 0.5, "diffuse_fresnel": 0.1, "diffuse_fresnel_factor": 0.5, "darkness": 1, "diffuse_toon_size": 0.5, "diffuse_toon_smooth": 0.1, "diffuse_intensity": 0.8, "alpha": 1, "specular_alpha": 1, "raytrace_transparency": {"fresnel": 0, "fresnel_factor": 1.25}, "raytrace_mirror": {"reflect_factor": 0, "fresnel": 0, "fresnel_factor": 1.25}, "specular_color": [1, 1, 1], "specular_intensity": 0.5, "specular_shader": "COOKTORR", "specular_hardness": 50, "specular_ior": 4, "specular_slope": 0.1, "specular_toon_size": 0.5, "specular_toon_smooth": 0.1, "emit": 0, "ambient": 1, "use_vertex_color_paint": false, "b4w_water": false, "b4w_water_shore_smoothing": true, "b4w_water_absorb_factor": 6, "b4w_water_dynamic": false, "b4w_waves_height": 1, "b4w_waves_length": 10, "b4w_generated_mesh": false, "b4w_water_num_cascads": 5, "b4w_water_subdivs": 64, "b4w_water_detailed_dist": 1000, "b4w_water_fog_color": [0.4, 0.6, 0.7], "b4w_water_fog_density": 0.06, "b4w_foam_factor": 0.5, "b4w_shallow_water_col": [0, 0.8, 0.3], "b4w_shore_water_col": [0, 0.9, 0.2], "b4w_shallow_water_col_fac": 1, "b4w_shore_water_col_fac": 0.5, "b4w_water_dst_noise_scale0": 0.05, "b4w_water_dst_noise_scale1": 0.03, "b4w_water_dst_noise_freq0": 1.3, "b4w_water_dst_noise_freq1": 1, "b4w_water_dir_min_shore_fac": 0.4, "b4w_water_dir_freq": 0.5, "b4w_water_dir_noise_scale": 0.05, "b4w_water_dir_noise_freq": 0.07, "b4w_water_dir_min_noise_fac": 0.5, "b4w_water_dst_min_fac": 0.2, "b4w_water_waves_hor_fac": 5, "b4w_water_sss_strength": 1, "b4w_water_sss_width": 0.45, "b4w_water_norm_uv_velocity": 0.05, "b4w_water_enable_caust": false, "b4w_water_caust_scale": 0.25, "b4w_water_caust_brightness": 0.5, "b4w_terrain": false, "b4w_dynamic_grass_size": "", "b4w_dynamic_grass_color": "", "b4w_do_not_render": false, "b4w_lens_flares": false, "b4w_collision": false, "b4w_use_ghost": false, "b4w_collision_id": "", "b4w_collision_margin": 0.03999999910593033, "b4w_collision_group": 128, "b4w_collision_mask": 65407, "b4w_double_sided_lighting": false, "b4w_wettable": false, "b4w_refractive": false, "b4w_refr_bump": 0.0010000000474974513, "b4w_render_above_all": false, "physics": {"friction": 0.5, "elasticity": 0}, "type": "SURFACE", "b4w_halo_sky_stars": false, "b4w_halo_stars_blend_height": 10.0, "b4w_halo_stars_min_height": 0.0, "halo": {"hardness": 50, "size": 0.5, "b4w_halo_rings_color": [1, 1, 1], "b4w_halo_lines_color": [1, 1, 1], "ring_count": 0, "line_count": 0, "star_tip_count": 0}, "use_transparency": false, "use_shadeless": false, "use_tangent_shading": false, "pass_index": 0, "offset_z": 0, "game_settings": {"alpha_blend": "OPAQUE", "use_backface_culling": true}, "uv_vc_key": "ColUVMapUVMap", "node_tree": {"nodes": [{"name": "Mix.001", "type": "MIX_RGB", "blend_type": "MULTIPLY", "use_clamp": false, "inputs": [{"name": "Fac", "identifier": "Fac", "is_linked": false, "default_value": 0.5}, {"name": "Color1", "identifier": "Color1", "is_linked": true, "default_value": [0.5, 0.5, 0.5, 1]}, {"name": "Color2", "identifier": "Color2", "is_linked": true, "default_value": [0.5, 0.5, 0.5, 1]}], "outputs": [{"name": "Color", "identifier": "Color", "is_linked": true, "default_value": [0, 0, 0, 0]}]}, {"name": "Geometry.001", "type": "GEOMETRY", "uv_layer": "UVMap", "color_layer": "", "inputs": [], "outputs": [{"name": "Global", "identifier": "Global", "is_linked": false, "default_value": [0, 0, 0]}, {"name": "Local", "identifier": "Local", "is_linked": false, "default_value": [0, 0, 0]}, {"name": "View", "identifier": "View", "is_linked": false, "default_value": [0, 0, 0]}, {"name": "Orco", "identifier": "Orco", "is_linked": false, "default_value": [0, 0, 0]}, {"name": "UV", "identifier": "UV", "is_linked": true, "default_value": [0, 0, 0]}, {"name": "Normal", "identifier": "Normal", "is_linked": false, "default_value": [0, 0, 0]}, {"name": "Vertex Color", "identifier": "Vertex Color", "is_linked": false, "default_value": [0, 0, 0, 0]}, {"name": "Vertex Alpha", "identifier": "Vertex Alpha", "is_linked": false, "default_value": 0}, {"name": "Front/Back", "identifier": "Front/Back", "is_linked": false, "default_value": 0}]}, {"name": "Separate RGB", "type": "SEPRGB", "inputs": [{"name": "Image", "identifier": "Image", "is_linked": true, "default_value": [0.8, 0.8, 0.8, 1]}], "outputs": [{"name": "R", "identifier": "R", "is_linked": true, "default_value": 0}, {"name": "G", "identifier": "G", "is_linked": false, "default_value": 0}, {"name": "B", "identifier": "B", "is_linked": false, "default_value": 0}]}, {"name": "Geometry", "type": "GEOMETRY", "uv_layer": "", "color_layer": "Col", "inputs": [], "outputs": [{"name": "Global", "identifier": "Global", "is_linked": false, "default_value": [0, 0, 0]}, {"name": "Local", "identifier": "Local", "is_linked": false, "default_value": [0, 0, 0]}, {"name": "View", "identifier": "View", "is_linked": false, "default_value": [0, 0, 0]}, {"name": "Orco", "identifier": "Orco", "is_linked": false, "default_value": [0, 0, 0]}, {"name": "UV", "identifier": "UV", "is_linked": false, "default_value": [0, 0, 0]}, {"name": "Normal", "identifier": "Normal", "is_linked": false, "default_value": [0, 0, 0]}, {"name": "Vertex Color", "identifier": "Vertex Color", "is_linked": true, "default_value": [0, 0, 0, 0]}, {"name": "Vertex Alpha", "identifier": "Vertex Alpha", "is_linked": false, "default_value": 0}, {"name": "Front/Back", "identifier": "Front/Back", "is_linked": false, "default_value": 0}]}, {"name": "Material.001", "type": "MATERIAL", "material_name": "constant_material_node.003", "specular_shader": "PHONG", "specular_hardness": 30, "specular_slope": 0.1, "specular_toon_size": 0.5, "specular_toon_smooth": 0.1, "specular_intensity": 0.1, "specular_ior": 4, "diffuse_shader": "LAMBERT", "use_shadeless": false, "use_tangent_shading": false, "specular_alpha": 1.0, "alpha": 1.0, "diffuse_intensity": 0.699999988079071, "roughness": 0.3, "diffuse_fresnel": 0.1, "diffuse_fresnel_factor": 0.5, "darkness": 1, "diffuse_toon_size": 0.5, "diffuse_toon_smooth": 0.1, "use_diffuse": true, "use_specular": true, "invert_normal": false, "inputs": [{"name": "Color", "identifier": "Color", "is_linked": true, "default_value": [0.8, 0.8, 0.8, 1]}, {"name": "Spec", "identifier": "Spec", "is_linked": false, "default_value": [1, 1, 1, 1]}, {"name": "DiffuseIntensity", "identifier": "DiffuseIntensity", "is_linked": false, "default_value": 0.7}, {"name": "Normal", "identifier": "Normal", "is_linked": false, "default_value": [0, 0, 0]}], "outputs": [{"name": "Color", "identifier": "Color", "is_linked": true, "default_value": [0, 0, 0, 0]}, {"name": "Alpha", "identifier": "Alpha", "is_linked": false, "default_value": 0}, {"name": "Normal", "identifier": "Normal", "is_linked": false, "default_value": [0, 0, 0]}]}, {"name": "Material", "type": "MATERIAL", "material_name": "constant_material_node.002", "specular_shader": "WARDISO", "specular_hardness": 50, "specular_slope": 0.2, "specular_toon_size": 0.5, "specular_toon_smooth": 0.1, "specular_intensity": 0.5, "specular_ior": 4, "diffuse_shader": "OREN_NAYAR", "use_shadeless": false, "use_tangent_shading": false, "specular_alpha": 1.0, "alpha": 1.0, "diffuse_intensity": 0.800000011920929, "roughness": 0.5, "diffuse_fresnel": 0.1, "diffuse_fresnel_factor": 0.5, "darkness": 1, "diffuse_toon_size": 0.5, "diffuse_toon_smooth": 0.1, "use_diffuse": true, "use_specular": true, "invert_normal": false, "inputs": [{"name": "Color", "identifier": "Color", "is_linked": true, "default_value": [0.8, 0.8, 0.8, 1]}, {"name": "Spec", "identifier": "Spec", "is_linked": false, "default_value": [1, 1, 1, 1]}, {"name": "DiffuseIntensity", "identifier": "DiffuseIntensity", "is_linked": false, "default_value": 0.8}, {"name": "Normal", "identifier": "Normal", "is_linked": false, "default_value": [0, 0, 0]}], "outputs": [{"name": "Color", "identifier": "Color", "is_linked": true, "default_value": [0, 0, 0, 0]}, {"name": "Alpha", "identifier": "Alpha", "is_linked": false, "default_value": 0}, {"name": "Normal", "identifier": "Normal", "is_linked": false, "default_value": [0, 0, 0]}]}, {"name": "RGB.001", "type": "RGB", "inputs": [], "outputs": [{"name": "Color", "identifier": "Color", "is_linked": true, "default_value": [1, 1, 1, 1]}]}, {"name": "RGB", "type": "RGB", "inputs": [], "outputs": [{"name": "Color", "identifier": "Color", "is_linked": true, "default_value": [0.25, 0.25, 0.25, 1]}]}, {"name": "Output", "type": "OUTPUT", "inputs": [{"name": "Color", "identifier": "Color", "is_linked": true, "default_value": [0, 0, 0, 1]}, {"name": "Alpha", "identifier": "Alpha", "is_linked": false, "default_value": 1}], "outputs": []}, {"name": "Texture.003", "type": "TEXTURE", "texture": {"uuid": "e6511b8e83573ef387fa450e2da041b8"}, "inputs": [{"name": "Vector", "identifier": "Vector", "is_linked": true, "default_value": [0, 0, 0]}], "outputs": [{"name": "Value", "identifier": "Value", "is_linked": false, "default_value": 0}, {"name": "Color", "identifier": "Color", "is_linked": true, "default_value": [0, 0, 0, 0]}, {"name": "Normal", "identifier": "Normal", "is_linked": false, "default_value": [0, 0, 0]}]}, {"name": "Separate RGB.001", "type": "SEPRGB", "inputs": [{"name": "Image", "identifier": "Image", "is_linked": true, "default_value": [0.8, 0.8, 0.8, 1]}], "outputs": [{"name": "R", "identifier": "R", "is_linked": true, "default_value": 0}, {"name": "G", "identifier": "G", "is_linked": false, "default_value": 0}, {"name": "B", "identifier": "B", "is_linked": false, "default_value": 0}]}, {"name": "Mix", "type": "MIX_RGB", "blend_type": "MIX", "use_clamp": false, "inputs": [{"name": "Fac", "identifier": "Fac", "is_linked": true, "default_value": 0.5}, {"name": "Color1", "identifier": "Color1", "is_linked": true, "default_value": [1, 0, 0, 1]}, {"name": "Color2", "identifier": "Color2", "is_linked": true, "default_value": [0, 1, 0, 1]}], "outputs": [{"name": "Color", "identifier": "Color", "is_linked": true, "default_value": [0, 0, 0, 0]}]}], "links": [{"from_node": {"name": "RGB"}, "to_node": {"name": "Material"}, "from_socket": {"identifier": "Color"}, "to_socket": {"identifier": "Color"}}, {"from_node": {"name": "RGB.001"}, "to_node": {"name": "Material.001"}, "from_socket": {"identifier": "Color"}, "to_socket": {"identifier": "Color"}}, {"from_node": {"name": "Geometry"}, "to_node": {"name": "Separate RGB"}, "from_socket": {"identifier": "Vertex Color"}, "to_socket": {"identifier": "Image"}}, {"from_node": {"name": "Separate RGB"}, "to_node": {"name": "Mix"}, "from_socket": {"identifier": "R"}, "to_socket": {"identifier": "Fac"}}, {"from_node": {"name": "Material"}, "to_node": {"name": "Mix"}, "from_socket": {"identifier": "Color"}, "to_socket": {"identifier": "Color2"}}, {"from_node": {"name": "Material.001"}, "to_node": {"name": "Mix"}, "from_socket": {"identifier": "Color"}, "to_socket": {"identifier": "Color1"}}, {"from_node": {"name": "Geometry.001"}, "to_node": {"name": "Texture.003"}, "from_socket": {"identifier": "UV"}, "to_socket": {"identifier": "Vector"}}, {"from_node": {"name": "Mix"}, "to_node": {"name": "Mix.001"}, "from_socket": {"identifier": "Color"}, "to_socket": {"identifier": "Color1"}}, {"from_node": {"name": "Texture.003"}, "to_node": {"name": "Separate RGB.001"}, "from_socket": {"identifier": "Color"}, "to_socket": {"identifier": "Image"}}, {"from_node": {"name": "Separate RGB.001"}, "to_node": {"name": "Mix.001"}, "from_socket": {"identifier": "R"}, "to_socket": {"identifier": "Color2"}}, {"from_node": {"name": "Mix.001"}, "to_node": {"name": "Output"}, "from_socket": {"identifier": "Color"}, "to_socket": {"identifier": "Color"}}], "animation_data": null}, "texture_slots": [], "uuid": "891d8d379ab46d805934a2cb26d71559", "source_uuid": "c5aa3ded7b01de49fa02c875c827edd3"}, {"use_orco_tex_coord": false, "name": "plane", "use_nodes": true, "diffuse_color": [0.8, 0.8, 0.8], "diffuse_shader": "LAMBERT", "roughness": 0.5, "diffuse_fresnel": 0.1, "diffuse_fresnel_factor": 0.5, "darkness": 1, "diffuse_toon_size": 0.5, "diffuse_toon_smooth": 0.1, "diffuse_intensity": 0.8, "alpha": 1, "specular_alpha": 1, "raytrace_transparency": {"fresnel": 0, "fresnel_factor": 1.25}, "raytrace_mirror": {"reflect_factor": 0.5, "fresnel": 0, "fresnel_factor": 1.25}, "specular_color": [1, 1, 1], "specular_intensity": 0.5, "specular_shader": "COOKTORR", "specular_hardness": 50, "specular_ior": 4, "specular_slope": 0.1, "specular_toon_size": 0.5, "specular_toon_smooth": 0.1, "emit": 0, "ambient": 1, "use_vertex_color_paint": false, "b4w_water": false, "b4w_water_shore_smoothing": true, "b4w_water_absorb_factor": 6, "b4w_water_dynamic": false, "b4w_waves_height": 1, "b4w_waves_length": 10, "b4w_generated_mesh": false, "b4w_water_num_cascads": 5, "b4w_water_subdivs": 64, "b4w_water_detailed_dist": 1000, "b4w_water_fog_color": [0.4, 0.6, 0.7], "b4w_water_fog_density": 0.06, "b4w_foam_factor": 0.5, "b4w_shallow_water_col": [0, 0.8, 0.3], "b4w_shore_water_col": [0, 0.9, 0.2], "b4w_shallow_water_col_fac": 1, "b4w_shore_water_col_fac": 0.5, "b4w_water_dst_noise_scale0": 0.05, "b4w_water_dst_noise_scale1": 0.03, "b4w_water_dst_noise_freq0": 1.3, "b4w_water_dst_noise_freq1": 1, "b4w_water_dir_min_shore_fac": 0.4, "b4w_water_dir_freq": 0.5, "b4w_water_dir_noise_scale": 0.05, "b4w_water_dir_noise_freq": 0.07, "b4w_water_dir_min_noise_fac": 0.5, "b4w_water_dst_min_fac": 0.2, "b4w_water_waves_hor_fac": 5, "b4w_water_sss_strength": 1, "b4w_water_sss_width": 0.45, "b4w_water_norm_uv_velocity": 0.05, "b4w_water_enable_caust": false, "b4w_water_caust_scale": 0.25, "b4w_water_caust_brightness": 0.5, "b4w_terrain": false, "b4w_dynamic_grass_size": "", "b4w_dynamic_grass_color": "", "b4w_do_not_render": false, "b4w_lens_flares": false, "b4w_collision": false, "b4w_use_ghost": false, "b4w_collision_id": "", "b4w_collision_margin": 0.03999999910593033, "b4w_collision_group": 128, "b4w_collision_mask": 65407, "b4w_double_sided_lighting": false, "b4w_wettable": false, "b4w_refractive": false, "b4w_refr_bump": 0.0010000000474974513, "b4w_render_above_all": false, "physics": {"friction": 0.5, "elasticity": 0}, "type": "SURFACE", "b4w_halo_sky_stars": false, "b4w_halo_stars_blend_height": 10.0, "b4w_halo_stars_min_height": 0.0, "halo": {"hardness": 50, "size": 0.5, "b4w_halo_rings_color": [1, 1, 1], "b4w_halo_lines_color": [1, 1, 1], "ring_count": 0, "line_count": 0, "star_tip_count": 0}, "use_transparency": false, "use_shadeless": false, "use_tangent_shading": false, "pass_index": 0, "offset_z": 0, "game_settings": {"alpha_blend": "OPAQUE", "use_backface_culling": true}, "uv_vc_key": "UVMapUVMap", "node_tree": {"nodes": [{"name": "Vector Math", "type": "VECT_MATH", "operation": "AVERAGE", "inputs": [{"name": "Vector", "identifier": "Vector", "is_linked": true, "default_value": [0.5, 0.5, 0.5]}, {"name": "Vector", "identifier": "Vector_001", "is_linked": false, "default_value": [0, 0, 0]}], "outputs": [{"name": "Vector", "identifier": "Vector", "is_linked": false, "default_value": [0, 0, 0]}, {"name": "Value", "identifier": "Value", "is_linked": true, "default_value": 0}]}, {"name": "Extended Material.001", "type": "MATERIAL_EXT", "material_name": "plane", "specular_shader": "COOKTORR", "specular_hardness": 50, "specular_slope": 0.1, "specular_toon_size": 0.5, "specular_toon_smooth": 0.1, "specular_intensity": 0.5, "specular_ior": 4, "diffuse_shader": "LAMBERT", "use_shadeless": false, "use_tangent_shading": false, "specular_alpha": 1.0, "alpha": 1.0, "diffuse_intensity": 0.800000011920929, "roughness": 0.5, "diffuse_fresnel": 0.1, "diffuse_fresnel_factor": 0.5, "darkness": 1, "diffuse_toon_size": 0.5, "diffuse_toon_smooth": 0.1, "use_diffuse": true, "use_specular": true, "invert_normal": false, "inputs": [{"name": "Color", "identifier": "Color", "is_linked": true, "default_value": [0.8, 0.8, 0.8, 1]}, {"name": "Spec", "identifier": "Spec", "is_linked": false, "default_value": [1, 1, 1, 1]}, {"name": "DiffuseIntensity", "identifier": "DiffuseIntensity", "is_linked": false, "default_value": 0.8}, {"name": "Normal", "identifier": "Normal", "is_linked": false, "default_value": [0, 0, 0]}, {"name": "Mirror", "identifier": "Mirror", "is_linked": false, "default_value": [1, 1, 1, 1]}, {"name": "Ambient", "identifier": "Ambient", "is_linked": false, "default_value": 1}, {"name": "Emit", "identifier": "Emit", "is_linked": false, "default_value": 0}, {"name": "SpecTra", "identifier": "SpecTra", "is_linked": false, "default_value": 1}, {"name": "Reflectivity", "identifier": "Reflectivity", "is_linked": false, "default_value": 0.5}, {"name": "Alpha", "identifier": "Alpha", "is_linked": false, "default_value": 1}, {"name": "Translucency", "identifier": "Translucency", "is_linked": false, "default_value": 0}], "outputs": [{"name": "Color", "identifier": "Color", "is_linked": true, "default_value": [0, 0, 0, 0]}, {"name": "Alpha", "identifier": "Alpha", "is_linked": false, "default_value": 0}, {"name": "Normal", "identifier": "Normal", "is_linked": false, "default_value": [0, 0, 0]}, {"name": "Diffuse", "identifier": "Diffuse", "is_linked": false, "default_value": [0, 0, 0, 0]}, {"name": "Spec", "identifier": "Spec", "is_linked": false, "default_value": [0, 0, 0, 0]}, {"name": "AO", "identifier": "AO", "is_linked": false, "default_value": [0, 0, 0, 0]}]}, {"name": "Group.004", "type": "GROUP", "node_tree_name": "B4W_SMOOTHSTEP.001", "node_group": {"uuid": "8b173179470c3e9517d954135c27f412"}, "inputs": [{"name": "Value", "identifier": "Input_1", "is_linked": true, "default_value": 0.5}, {"name": "Edge0", "identifier": "Input_5", "is_linked": false, "default_value": 0.58}, {"name": "Edge1", "identifier": "Input_7", "is_linked": false, "default_value": 0.25}], "outputs": [{"name": "Value", "identifier": "Output_3", "is_linked": true, "default_value": 0}]}, {"name": "Mix.003", "type": "MIX_RGB", "blend_type": "MIX", "use_clamp": false, "inputs": [{"name": "Fac", "identifier": "Fac", "is_linked": true, "default_value": 0.5}, {"name": "Color1", "identifier": "Color1", "is_linked": false, "default_value": [0.6, 0.6, 0.6, 1]}, {"name": "Color2", "identifier": "Color2", "is_linked": true, "default_value": [0.5, 0.5, 0.5, 1]}], "outputs": [{"name": "Color", "identifier": "Color", "is_linked": true, "default_value": [0, 0, 0, 0]}]}, {"name": "Geometry", "type": "GEOMETRY", "uv_layer": "UVMap", "color_layer": "", "inputs": [], "outputs": [{"name": "Global", "identifier": "Global", "is_linked": false, "default_value": [0, 0, 0]}, {"name": "Local", "identifier": "Local", "is_linked": false, "default_value": [0, 0, 0]}, {"name": "View", "identifier": "View", "is_linked": false, "default_value": [0, 0, 0]}, {"name": "Orco", "identifier": "Orco", "is_linked": false, "default_value": [0, 0, 0]}, {"name": "UV", "identifier": "UV", "is_linked": true, "default_value": [0, 0, 0]}, {"name": "Normal", "identifier": "Normal", "is_linked": false, "default_value": [0, 0, 0]}, {"name": "Vertex Color", "identifier": "Vertex Color", "is_linked": false, "default_value": [0, 0, 0, 0]}, {"name": "Vertex Alpha", "identifier": "Vertex Alpha", "is_linked": false, "default_value": 0}, {"name": "Front/Back", "identifier": "Front/Back", "is_linked": false, "default_value": 0}]}, {"name": "Output.001", "type": "OUTPUT", "inputs": [{"name": "Color", "identifier": "Color", "is_linked": true, "default_value": [0, 0, 0, 1]}, {"name": "Alpha", "identifier": "Alpha", "is_linked": false, "default_value": 1}], "outputs": []}, {"name": "Mapping.001", "type": "MAPPING", "translation": [0, -0.23, 0], "rotation": [0, 0, 0], "scale": [0.59, 0.82, 1], "vector_type": "POINT", "use_min": false, "use_max": false, "min": [0, 0, 0], "max": [1, 1, 1], "inputs": [{"name": "Vector", "identifier": "Vector", "is_linked": true, "default_value": [0, 0, 0]}], "outputs": [{"name": "Vector", "identifier": "Vector", "is_linked": true, "default_value": [0, 0, 0]}]}, {"name": "Texture", "type": "TEXTURE", "texture": {"uuid": "fee7ebc79a9914564b68b3d957ad6b94"}, "inputs": [{"name": "Vector", "identifier": "Vector", "is_linked": true, "default_value": [0, 0, 0]}], "outputs": [{"name": "Value", "identifier": "Value", "is_linked": false, "default_value": 0}, {"name": "Color", "identifier": "Color", "is_linked": true, "default_value": [0, 0, 0, 0]}, {"name": "Normal", "identifier": "Normal", "is_linked": false, "default_value": [0, 0, 0]}]}, {"name": "Mapping", "type": "MAPPING", "translation": [-0.9834, 0.148, 0], "rotation": [0, 0, 0], "scale": [48, 48, 1], "vector_type": "POINT", "use_min": false, "use_max": false, "min": [0, 0, 0], "max": [1, 1, 1], "inputs": [{"name": "Vector", "identifier": "Vector", "is_linked": true, "default_value": [0, 0, 0]}], "outputs": [{"name": "Vector", "identifier": "Vector", "is_linked": true, "default_value": [0, 0, 0]}]}], "links": [{"from_node": {"name": "Geometry"}, "to_node": {"name": "Mapping"}, "from_socket": {"identifier": "UV"}, "to_socket": {"identifier": "Vector"}}, {"from_node": {"name": "Mapping"}, "to_node": {"name": "Texture"}, "from_socket": {"identifier": "Vector"}, "to_socket": {"identifier": "Vector"}}, {"from_node": {"name": "Mix.003"}, "to_node": {"name": "Output.001"}, "from_socket": {"identifier": "Color"}, "to_socket": {"identifier": "Color"}}, {"from_node": {"name": "Extended Material.001"}, "to_node": {"name": "Mix.003"}, "from_socket": {"identifier": "Color"}, "to_socket": {"identifier": "Color2"}}, {"from_node": {"name": "Texture"}, "to_node": {"name": "Extended Material.001"}, "from_socket": {"identifier": "Color"}, "to_socket": {"identifier": "Color"}}, {"from_node": {"name": "Vector Math"}, "to_node": {"name": "Group.004"}, "from_socket": {"identifier": "Value"}, "to_socket": {"identifier": "Input_1"}}, {"from_node": {"name": "Geometry"}, "to_node": {"name": "Mapping.001"}, "from_socket": {"identifier": "UV"}, "to_socket": {"identifier": "Vector"}}, {"from_node": {"name": "Group.004"}, "to_node": {"name": "Mix.003"}, "from_socket": {"identifier": "Output_3"}, "to_socket": {"identifier": "Fac"}}, {"from_node": {"name": "Mapping.001"}, "to_node": {"name": "Vector Math"}, "from_socket": {"identifier": "Vector"}, "to_socket": {"identifier": "Vector"}}], "animation_data": null}, "texture_slots": [], "uuid": "a9e71b06fcefbda362d7b27a39ce85fa", "source_uuid": "81df9a466b4b392419141cf552446045"}, {"use_orco_tex_coord": true, "name": "ramp_vector", "use_nodes": true, "diffuse_color": [0.8, 0.8, 0.8], "diffuse_shader": "LAMBERT", "roughness": 0.5, "diffuse_fresnel": 0.1, "diffuse_fresnel_factor": 0.5, "darkness": 1, "diffuse_toon_size": 0.5, "diffuse_toon_smooth": 0.1, "diffuse_intensity": 0.8, "alpha": 1, "specular_alpha": 1, "raytrace_transparency": {"fresnel": 0, "fresnel_factor": 1.25}, "raytrace_mirror": {"reflect_factor": 0, "fresnel": 0, "fresnel_factor": 1.25}, "specular_color": [1, 1, 1], "specular_intensity": 0.5, "specular_shader": "COOKTORR", "specular_hardness": 50, "specular_ior": 4, "specular_slope": 0.1, "specular_toon_size": 0.5, "specular_toon_smooth": 0.1, "emit": 0, "ambient": 1, "use_vertex_color_paint": false, "b4w_water": false, "b4w_water_shore_smoothing": true, "b4w_water_absorb_factor": 6, "b4w_water_dynamic": false, "b4w_waves_height": 1, "b4w_waves_length": 10, "b4w_generated_mesh": false, "b4w_water_num_cascads": 5, "b4w_water_subdivs": 64, "b4w_water_detailed_dist": 1000, "b4w_water_fog_color": [0.4, 0.6, 0.7], "b4w_water_fog_density": 0.06, "b4w_foam_factor": 0.5, "b4w_shallow_water_col": [0, 0.8, 0.3], "b4w_shore_water_col": [0, 0.9, 0.2], "b4w_shallow_water_col_fac": 1, "b4w_shore_water_col_fac": 0.5, "b4w_water_dst_noise_scale0": 0.05, "b4w_water_dst_noise_scale1": 0.03, "b4w_water_dst_noise_freq0": 1.3, "b4w_water_dst_noise_freq1": 1, "b4w_water_dir_min_shore_fac": 0.4, "b4w_water_dir_freq": 0.5, "b4w_water_dir_noise_scale": 0.05, "b4w_water_dir_noise_freq": 0.07, "b4w_water_dir_min_noise_fac": 0.5, "b4w_water_dst_min_fac": 0.2, "b4w_water_waves_hor_fac": 5, "b4w_water_sss_strength": 1, "b4w_water_sss_width": 0.45, "b4w_water_norm_uv_velocity": 0.05, "b4w_water_enable_caust": false, "b4w_water_caust_scale": 0.25, "b4w_water_caust_brightness": 0.5, "b4w_terrain": false, "b4w_dynamic_grass_size": "", "b4w_dynamic_grass_color": "", "b4w_do_not_render": false, "b4w_lens_flares": false, "b4w_collision": false, "b4w_use_ghost": false, "b4w_collision_id": "", "b4w_collision_margin": 0.03999999910593033, "b4w_collision_group": 128, "b4w_collision_mask": 65407, "b4w_double_sided_lighting": false, "b4w_wettable": false, "b4w_refractive": false, "b4w_refr_bump": 0.0010000000474974513, "b4w_render_above_all": false, "physics": {"friction": 0.5, "elasticity": 0}, "type": "SURFACE", "b4w_halo_sky_stars": false, "b4w_halo_stars_blend_height": 10.0, "b4w_halo_stars_min_height": 0.0, "halo": {"hardness": 50, "size": 0.5, "b4w_halo_rings_color": [1, 1, 1], "b4w_halo_lines_color": [1, 1, 1], "ring_count": 0, "line_count": 0, "star_tip_count": 0}, "use_transparency": false, "use_shadeless": false, "use_tangent_shading": false, "pass_index": 0, "offset_z": 0, "game_settings": {"alpha_blend": "OPAQUE", "use_backface_culling": true}, "uv_vc_key": "", "node_tree": {"nodes": [{"name": "Math.013", "type": "MATH", "operation": "MULTIPLY", "use_clamp": false, "inputs": [{"name": "Value", "identifier": "Value", "is_linked": true, "default_value": 0.5}, {"name": "Value", "identifier": "Value_001", "is_linked": false, "default_value": 0.5}], "outputs": [{"name": "Value", "identifier": "Value", "is_linked": true, "default_value": 0}]}, {"name": "ColorRamp", "type": "VALTORGB", "color_ramp": {"elements": [{"position": 0.043, "color": [1, 0, 0, 1]}, {"position": 0.286, "color": [0, 1, 0, 1]}, {"position": 0.62, "color": [1, 0, 0, 1]}, {"position": 0.936, "color": [0, 0, 1, 1]}], "interpolation": "LINEAR"}, "inputs": [{"name": "Fac", "identifier": "Fac", "is_linked": true, "default_value": 0.5}], "outputs": [{"name": "Color", "identifier": "Color", "is_linked": true, "default_value": [0, 0, 0, 0]}, {"name": "Alpha", "identifier": "Alpha", "is_linked": false, "default_value": 0}]}, {"name": "Output.001", "type": "OUTPUT", "inputs": [{"name": "Color", "identifier": "Color", "is_linked": true, "default_value": [0, 0, 0, 1]}, {"name": "Alpha", "identifier": "Alpha", "is_linked": false, "default_value": 1}], "outputs": []}, {"name": "Geometry", "type": "GEOMETRY", "uv_layer": "", "color_layer": "", "inputs": [], "outputs": [{"name": "Global", "identifier": "Global", "is_linked": false, "default_value": [0, 0, 0]}, {"name": "Local", "identifier": "Local", "is_linked": false, "default_value": [0, 0, 0]}, {"name": "View", "identifier": "View", "is_linked": false, "default_value": [0, 0, 0]}, {"name": "Orco", "identifier": "Orco", "is_linked": true, "default_value": [0, 0, 0]}, {"name": "UV", "identifier": "UV", "is_linked": false, "default_value": [0, 0, 0]}, {"name": "Normal", "identifier": "Normal", "is_linked": false, "default_value": [0, 0, 0]}, {"name": "Vertex Color", "identifier": "Vertex Color", "is_linked": false, "default_value": [0, 0, 0, 0]}, {"name": "Vertex Alpha", "identifier": "Vertex Alpha", "is_linked": false, "default_value": 0}, {"name": "Front/Back", "identifier": "Front/Back", "is_linked": false, "default_value": 0}]}, {"name": "Math.012", "type": "MATH", "operation": "ADD", "use_clamp": false, "inputs": [{"name": "Value", "identifier": "Value", "is_linked": true, "default_value": 0.5}, {"name": "Value", "identifier": "Value_001", "is_linked": false, "default_value": 1}], "outputs": [{"name": "Value", "identifier": "Value", "is_linked": true, "default_value": 0}]}, {"name": "Separate RGB.001", "type": "SEPRGB", "inputs": [{"name": "Image", "identifier": "Image", "is_linked": true, "default_value": [0.8, 0.8, 0.8, 1]}], "outputs": [{"name": "R", "identifier": "R", "is_linked": false, "default_value": 0}, {"name": "G", "identifier": "G", "is_linked": true, "default_value": 0}, {"name": "B", "identifier": "B", "is_linked": false, "default_value": 0}]}], "links": [{"from_node": {"name": "Math.012"}, "to_node": {"name": "Math.013"}, "from_socket": {"identifier": "Value"}, "to_socket": {"identifier": "Value"}}, {"from_node": {"name": "Separate RGB.001"}, "to_node": {"name": "Math.012"}, "from_socket": {"identifier": "G"}, "to_socket": {"identifier": "Value"}}, {"from_node": {"name": "Math.013"}, "to_node": {"name": "ColorRamp"}, "from_socket": {"identifier": "Value"}, "to_socket": {"identifier": "Fac"}}, {"from_node": {"name": "ColorRamp"}, "to_node": {"name": "Output.001"}, "from_socket": {"identifier": "Color"}, "to_socket": {"identifier": "Color"}}, {"from_node": {"name": "Geometry"}, "to_node": {"name": "Separate RGB.001"}, "from_socket": {"identifier": "Orco"}, "to_socket": {"identifier": "Image"}}], "animation_data": null}, "texture_slots": [], "uuid": "3a535f8f2da1cb74c82d875a976e6de2", "source_uuid": "3a535f8f2da1cb74c82d875a976e6de2"}], "meshes": [{"name": "Colorramp", "uuid": "fbbaf2a5bd7a5e920cf468f4347a078f", "materials": [{"uuid": "f0ea9c86d107f8dd6caf0704c1e3c8d6"}, {"uuid": "891d8d379ab46d805934a2cb26d71559"}], "b4w_vertex_anim": [], "vertex_groups": [], "uv_textures": ["UVMap"], "active_vcol_name": "Col", "submeshes": [{"boundings": {"bb": {"max_x": 0.36172, "max_y": 0.36911, "max_z": 0.8606, "min_x": -0.36172, "min_y": -0.36004, "min_z": 0.01298}, "be_ax": [0.57541, 0.68446, 0.7549], "be_cen": [-0.00145, 0.01058, 0.43462], "rbb": {"rbb_c": [-0.0052925776690244675, 0.03056184947490692, 0.37262019515037537], "rbb_s": [0.36168015003204346, 0.4302215874195099, 0.47449782490730286]}, "caxis_x": [0.999877393245697, 0.005609211046248674, 0.01462098304182291], "caxis_y": [0.0, 0.933650016784668, -0.35818660259246826], "caxis_z": [-0.01566002517938614, 0.3581426739692688, 0.9335355162620544]}, "base_length": 2422, "indices": [0, 11694], "position": [0, 7266], "texcoord": [7266, 4844], "shade_tangs": [0, 0], "normal": [0, 7266], "tangent": [7266, 9688], "group": [0, 0], "color": [0, 0], "vertex_colors": [], "uv_layers": ["UVMap"]}, {"boundings": {"bb": {"max_x": 0.37248, "max_y": 0.37114, "max_z": 0.8254, "min_x": -0.37248, "min_y": -0.39393, "min_z": 0.00098}, "be_ax": [0.57122, 0.7275, 0.77044], "be_cen": [-0.00176, -0.00167, 0.41157], "rbb": {"rbb_c": [-0.006018972955644131, 0.01961091160774231, 0.3493877351284027], "rbb_s": [0.3724200129508972, 0.4743046760559082, 0.5023058652877808]}, "caxis_x": [0.9998499751091003, 0.008170081302523613, 0.015273435972630978], "caxis_y": [0.0, 0.8817709684371948, -0.4716777801513672], "caxis_z": [-0.01732131838798523, 0.4716070294380188, 0.8816387057304382]}, "base_length": 4848, "indices": [11694, 14076], "position": [12110, 14544], "texcoord": [26654, 9696], "shade_tangs": [0, 0], "normal": [16954, 14544], "tangent": [31498, 19392], "group": [0, 0], "color": [0, 4848], "vertex_colors": [{"name": "Col", "mask": 4}], "uv_layers": ["UVMap"]}], "b4w_shape_keys": [], "b4w_boundings": {"bb": {"max_x": 0.37248, "max_y": 0.37114, "max_z": 0.8606, "min_x": -0.37248, "min_y": -0.39393, "min_z": 0.00098}, "be_ax": [0.58784, 0.72211, 0.77962], "be_cen": [-0.00157, 0.00048, 0.42829], "bs_rad": 0.54298, "bc_rad": 0.39669, "bs_cen": [0.00737, 0.00478, 0.36877], "bc_cen": [-0.00141, -0.00286, 0.43079], "bb_src": {"max_x": 0.37248, "max_y": 0.37114, "max_z": 0.8606, "min_x": -0.37248, "min_y": -0.39393, "min_z": 0.00098}, "rbb": {"rbb_c": [-0.005516300909221172, 0.027374736964702606, 0.3545856475830078], "rbb_s": [0.3724323809146881, 0.4574987590312958, 0.493937224149704]}, "caxis_x": [0.9998832941055298, 0.0061863926239311695, 0.013970700092613697], "caxis_y": [0.0, 0.9143646955490112, -0.40489158034324646], "caxis_z": [-0.015279133804142475, 0.4048443138599396, 0.9142580032348633]}, "is_boundings_overridden": false}, {"name": "floor", "uuid": "be0bcfadf26968c0781da84b591259fb", "materials": [{"uuid": "a9e71b06fcefbda362d7b27a39ce85fa"}], "b4w_vertex_anim": [], "vertex_groups": [], "uv_textures": ["UVMap"], "active_vcol_name": null, "submeshes": [{"boundings": {"bb": {"max_x": 24, "max_y": 32, "max_z": 8, "min_x": -24, "min_y": -8, "min_z": 0}, "be_ax": [41.5084, 34.77326, 6.89064], "be_cen": [0, 11.64848, 3.56279], "rbb": {"rbb_c": [9.5367431640625e-07, 11.9841947555542, 3.4450936317443848], "rbb_s": [24.0, 20.10576820373535, 3.984144687652588]}, "caxis_x": [1.0, 0.0, 0.0], "caxis_y": [0.0, 0.9995946884155273, -0.028468286618590355], "caxis_z": [0.0, 0.028468286618590355, 0.9995946884155273]}, "base_length": 16, "indices": [25770, 42], "position": [36350, 48], "texcoord": [36398, 32], "shade_tangs": [0, 0], "normal": [50890, 48], "tangent": [50938, 64], "group": [0, 0], "color": [0, 0], "vertex_colors": [], "uv_layers": ["UVMap"]}], "b4w_shape_keys": [], "b4w_boundings": {"bb": {"max_x": 24, "max_y": 32, "max_z": 8, "min_x": -24, "min_y": -8, "min_z": 0}, "be_ax": [41.5084, 34.77326, 6.89064], "be_cen": [0, 11.64848, 3.56279], "bs_rad": 32.85697, "bc_rad": 32.58066, "bs_cen": [0.29905, 10.18858, 3.66047], "bc_cen": [0.31218, 10.31089, 4], "bb_src": {"max_x": 24, "max_y": 32, "max_z": 8, "min_x": -24, "min_y": -8, "min_z": 0}, "rbb": {"rbb_c": [9.5367431640625e-07, 11.9841947555542, 3.4450936317443848], "rbb_s": [24.0, 20.10576820373535, 3.984144687652588]}, "caxis_x": [1.0, 0.0, 0.0], "caxis_y": [0.0, 0.9995946884155273, -0.028468286618590355], "caxis_z": [0.0, 0.028468286618590355, 0.9995946884155273]}, "is_boundings_overridden": false}, {"name": "Texture+Colorramp", "uuid": "d8ea533423df25ae4678f28e9680282e", "materials": [{"uuid": "3a535f8f2da1cb74c82d875a976e6de2"}, {"uuid": "891d8d379ab46d805934a2cb26d71559"}], "b4w_vertex_anim": [], "vertex_groups": [], "uv_textures": ["UVMap"], "active_vcol_name": "Col", "submeshes": [{"boundings": {"bb": {"max_x": 0.36172, "max_y": 0.36911, "max_z": 0.8606, "min_x": -0.36172, "min_y": -0.36004, "min_z": 0.01298}, "be_ax": [0.57541, 0.68446, 0.7549], "be_cen": [-0.00145, 0.01058, 0.43462], "rbb": {"rbb_c": [-0.0052925776690244675, 0.03056184947490692, 0.37262019515037537], "rbb_s": [0.36168015003204346, 0.4302215874195099, 0.47449782490730286]}, "caxis_x": [0.999877393245697, 0.005609211046248674, 0.01462098304182291], "caxis_y": [0.0, 0.933650016784668, -0.35818660259246826], "caxis_z": [-0.01566002517938614, 0.3581426739692688, 0.9335355162620544]}, "base_length": 2416, "indices": [25812, 11694], "position": [36430, 7248], "texcoord": [0, 0], "shade_tangs": [0, 0], "normal": [51002, 7248], "tangent": [0, 0], "group": [0, 0], "color": [0, 0], "vertex_colors": [], "uv_layers": []}, {"boundings": {"bb": {"max_x": 0.37248, "max_y": 0.37114, "max_z": 0.8254, "min_x": -0.37248, "min_y": -0.39393, "min_z": 0.00098}, "be_ax": [0.57122, 0.7275, 0.77044], "be_cen": [-0.00176, -0.00167, 0.41157], "rbb": {"rbb_c": [-0.006018972955644131, 0.01961091160774231, 0.3493877351284027], "rbb_s": [0.3724200129508972, 0.4743046760559082, 0.5023058652877808]}, "caxis_x": [0.9998499751091003, 0.008170081302523613, 0.015273435972630978], "caxis_y": [0.0, 0.8817709684371948, -0.4716777801513672], "caxis_z": [-0.01732131838798523, 0.4716070294380188, 0.8816387057304382]}, "base_length": 4848, "indices": [37506, 14076], "position": [43678, 14544], "texcoord": [58222, 9696], "shade_tangs": [0, 0], "normal": [58250, 14544], "tangent": [72794, 19392], "group": [0, 0], "color": [4848, 4848], "vertex_colors": [{"name": "Col", "mask": 4}], "uv_layers": ["UVMap"]}], "b4w_shape_keys": [], "b4w_boundings": {"bb": {"max_x": 0.37248, "max_y": 0.37114, "max_z": 0.8606, "min_x": -0.37248, "min_y": -0.39393, "min_z": 0.00098}, "be_ax": [0.58784, 0.72211, 0.77962], "be_cen": [-0.00157, 0.00048, 0.42829], "bs_rad": 0.54298, "bc_rad": 0.39669, "bs_cen": [0.00737, 0.00478, 0.36877], "bc_cen": [-0.00141, -0.00286, 0.43079], "bb_src": {"max_x": 0.37248, "max_y": 0.37114, "max_z": 0.8606, "min_x": -0.37248, "min_y": -0.39393, "min_z": 0.00098}, "rbb": {"rbb_c": [-0.005516300909221172, 0.027374736964702606, 0.3545856475830078], "rbb_s": [0.3724323809146881, 0.4574987590312958, 0.493937224149704]}, "caxis_x": [0.9998832941055298, 0.0061863926239311695, 0.013970700092613697], "caxis_y": [0.0, 0.9143646955490112, -0.40489158034324646], "caxis_z": [-0.015279133804142475, 0.4048443138599396, 0.9142580032348633]}, "is_boundings_overridden": false}], "armatures": [], "cameras": [{"name": "Camera", "uuid": "b6795846bc31d65d265ab395507bf8fb", "type": "PERSP", "angle": 0.50338, "angle_y": 0.50338, "sensor_fit": "VERTICAL", "ortho_scale": 7.314, "clip_start": 0.1, "clip_end": 100, "dof_distance": 0, "b4w_dof_front_start": 1, "b4w_dof_front_end": 5, "b4w_dof_rear_start": 1, "b4w_dof_rear_end": 5, "b4w_dof_power": 2, "b4w_dof_bokeh": false, "b4w_dof_bokeh_intensity": 0.3, "b4w_dof_foreground_blur": false, "b4w_move_style": "TARGET", "b4w_hover_zero_level": 0.0, "b4w_trans_velocity": 1, "b4w_rot_velocity": 1, "b4w_zoom_velocity": 0.1, "b4w_use_target_distance_limits": true, "b4w_distance_min": 1, "b4w_distance_max": 7.57, "b4w_use_horizontal_clamping": false, "b4w_rotation_left_limit": -0.7853981852531433, "b4w_rotation_right_limit": 0.7853981852531433, "b4w_horizontal_clamping_type": "LOCAL", "b4w_use_vertical_clamping": true, "b4w_rotation_down_limit": 0.0, "b4w_rotation_up_limit": 1.5707963705062866, "b4w_vertical_clamping_type": "WORLD", "b4w_horizontal_translation_min": -10, "b4w_horizontal_translation_max": 10, "b4w_vertical_translation_min": -10, "b4w_vertical_translation_max": 10, "b4w_use_zooming": false, "b4w_hover_angle_min": 0.0, "b4w_hover_angle_max": 1.5707963705062866, "b4w_enable_hover_hor_rotation": true, "b4w_use_panning": false, "b4w_use_pivot_limits": false, "b4w_pivot_z_min": 0.0, "b4w_pivot_z_max": 10.0, "b4w_target": [0, 0.5, 0.4], "dof_object": null}], "curves": [], "lamps": [{"animation_data": null, "name": "Lamp", "uuid": "b601adeb4c589784166684dc99cb5858", "type": "SUN", "energy": 0.5, "distance": 30, "use_diffuse": true, "use_specular": true, "falloff_type": null, "clip_start": 0.1, "clip_end": 30.0, "spot_size": null, "spot_blend": null, "b4w_generate_shadows": true, "b4w_dynamic_intensity": false, "color": [1, 1, 1]}], "sounds": [], "speakers": [], "particles": [], "objects": [{"name": "Colorramp", "uuid": "1d0a925e7df29d95b7af567511ed015f", "type": "MESH", "body_text": null, "data": {"uuid": "fbbaf2a5bd7a5e920cf468f4347a078f"}, "proxy": null, "dupli_group": null, "parent": null, "b4w_viewport_alignment": null, "pinverse_tsr": null, "parent_type": "OBJECT", "parent_bone": "", "b4w_cluster_data": {"cluster_id": -1, "cluster_center": null, "cluster_radius": 0}, "modifiers": [], "constraints": [], "particle_systems": [], "animation_data": null, "b4w_do_not_batch": false, "b4w_dynamic_geometry": false, "b4w_do_not_cull": false, "b4w_disable_fogging": false, "b4w_do_not_render": false, "b4w_hidden_on_load": false, "b4w_hide_chldr_on_load": false, "b4w_shadow_cast": true, "b4w_shadow_receive": false, "b4w_reflexible": true, "b4w_reflexible_only": false, "b4w_reflective": false, "b4w_reflection_type": "PLANE", "b4w_caustics": false, "b4w_wind_bending": false, "b4w_wind_bending_angle": 10, "b4w_wind_bending_freq": 0.25, "b4w_detail_bending_amp": 0.1, "b4w_detail_bending_freq": 1, "b4w_branch_bending_amp": 0.3, "b4w_main_bend_stiffness_col": "", "b4w_detail_bend_colors": {"leaves_stiffness_col": "", "leaves_phase_col": "", "overall_stiffness_col": ""}, "lod_levels": [], "b4w_proxy_inherit_anim": true, "b4w_selectable": false, "b4w_outlining": false, "b4w_billboard": false, "b4w_pres_glob_orientation": false, "b4w_billboard_geometry": "SPHERICAL", "b4w_outline_settings": {"outline_duration": 1, "outline_period": 1, "outline_relapses": 0}, "b4w_outline_on_select": false, "b4w_use_default_animation": false, "b4w_anim_behavior": "CYCLIC", "b4w_animation_mixing": false, "b4w_shadow_cast_only": false, "b4w_collision": false, "b4w_collision_id": "", "b4w_vehicle": false, "b4w_vehicle_settings": null, "b4w_character": false, "b4w_character_settings": null, "b4w_floating": false, "b4w_floating_settings": null, "pose": null, "field": null, "b4w_correct_bounding_offset": "AUTO", "game": {"physics_type": "STATIC", "use_ghost": false, "use_sleep": false, "mass": 1, "velocity_min": 0, "velocity_max": 0, "damping": 0.04, "rotation_damping": 0.1, "lock_location_x": false, "lock_location_y": false, "lock_location_z": false, "lock_rotation_x": false, "lock_rotation_y": false, "lock_rotation_z": false, "collision_margin": 0.03999999910593033, "collision_group": 1, "collision_mask": 65535, "use_collision_bounds": false, "collision_bounds_type": "BOX", "use_collision_compound": false}, "pass_index": 0, "location": [-0.5, 0.5, 0], "rotation_quaternion": [1, 0, 0, 0], "scale": [1, 1, 1], "b4w_object_tags": null, "b4w_custom_prop": null, "b4w_anchor": null}, {"name": "Colorramp_anotation", "uuid": "f2b1b87f4e97a656433d5c0a80d7bfde", "type": "EMPTY", "body_text": null, "data": "", "proxy": null, "dupli_group": null, "parent": {"uuid": "1d0a925e7df29d95b7af567511ed015f"}, "b4w_viewport_alignment": null, "parent_type": "OBJECT", "parent_bone": "", "b4w_cluster_data": {"cluster_id": -1, "cluster_center": null, "cluster_radius": 0}, "modifiers": [], "constraints": [], "particle_systems": [], "animation_data": null, "b4w_do_not_batch": false, "b4w_dynamic_geometry": false, "b4w_do_not_cull": false, "b4w_disable_fogging": false, "b4w_do_not_render": false, "b4w_hidden_on_load": false, "b4w_hide_chldr_on_load": false, "b4w_shadow_cast": false, "b4w_shadow_receive": false, "b4w_reflexible": false, "b4w_reflexible_only": false, "b4w_reflective": false, "b4w_reflection_type": "PLANE", "b4w_caustics": false, "b4w_wind_bending": false, "b4w_wind_bending_angle": 10, "b4w_wind_bending_freq": 0.25, "b4w_detail_bending_amp": 0.1, "b4w_detail_bending_freq": 1, "b4w_branch_bending_amp": 0.3, "b4w_main_bend_stiffness_col": "", "b4w_detail_bend_colors": {"leaves_stiffness_col": "", "leaves_phase_col": "", "overall_stiffness_col": ""}, "lod_levels": [], "b4w_proxy_inherit_anim": true, "b4w_selectable": false, "b4w_outlining": false, "b4w_billboard": false, "b4w_pres_glob_orientation": false, "b4w_billboard_geometry": "SPHERICAL", "b4w_outline_settings": {"outline_duration": 1, "outline_period": 1, "outline_relapses": 0}, "b4w_outline_on_select": false, "b4w_use_default_animation": false, "b4w_anim_behavior": "CYCLIC", "b4w_animation_mixing": false, "b4w_shadow_cast_only": false, "b4w_collision": false, "b4w_collision_id": "", "b4w_vehicle": false, "b4w_vehicle_settings": null, "b4w_character": false, "b4w_character_settings": null, "b4w_floating": false, "b4w_floating_settings": null, "pose": null, "field": null, "b4w_correct_bounding_offset": "AUTO", "game": {"physics_type": "NO_COLLISION", "use_ghost": false, "use_sleep": false, "mass": 1, "velocity_min": 0, "velocity_max": 0, "damping": 0.04, "rotation_damping": 0.1, "lock_location_x": false, "lock_location_y": false, "lock_location_z": false, "lock_rotation_x": false, "lock_rotation_y": false, "lock_rotation_z": false, "collision_margin": 0.03999999910593033, "collision_group": 1, "collision_mask": 65535, "use_collision_bounds": false, "collision_bounds_type": "BOX", "use_collision_compound": false}, "pass_index": 0, "pinverse_tsr": [0.72991, -1.19469, 0, 1, 0, 0, 0, 1], "location": [0, 0.03854, 0.93638], "rotation_quaternion": [1, 0, 0, 0], "scale": [1, 1, 1], "b4w_object_tags": {"title": "Color Ramp + Texture", "description": "", "category": ""}, "b4w_custom_prop": null, "b4w_anchor": {"type": "ANNOTATION", "detect_visibility": false, "element_id": "", "max_width": 250}}, {"name": "floor", "uuid": "0fc3dd6ef23f207da411726f0182a458", "type": "MESH", "body_text": null, "data": {"uuid": "be0bcfadf26968c0781da84b591259fb"}, "proxy": null, "dupli_group": null, "parent": null, "b4w_viewport_alignment": null, "pinverse_tsr": null, "parent_type": "OBJECT", "parent_bone": "", "b4w_cluster_data": {"cluster_id": -1, "cluster_center": null, "cluster_radius": 0}, "modifiers": [], "constraints": [{"name": "REFLECTION PLANE", "target": null, "mute": true, "type": "LOCKED_TRACK"}], "particle_systems": [], "animation_data": null, "b4w_do_not_batch": false, "b4w_dynamic_geometry": false, "b4w_do_not_cull": false, "b4w_disable_fogging": false, "b4w_do_not_render": false, "b4w_hidden_on_load": false, "b4w_hide_chldr_on_load": false, "b4w_shadow_cast": false, "b4w_shadow_receive": true, "b4w_reflexible": false, "b4w_reflexible_only": false, "b4w_reflective": true, "b4w_reflection_type": "PLANE", "b4w_caustics": false, "b4w_wind_bending": false, "b4w_wind_bending_angle": 10, "b4w_wind_bending_freq": 0.25, "b4w_detail_bending_amp": 0.1, "b4w_detail_bending_freq": 1, "b4w_branch_bending_amp": 0.3, "b4w_main_bend_stiffness_col": "", "b4w_detail_bend_colors": {"leaves_stiffness_col": "", "leaves_phase_col": "", "overall_stiffness_col": ""}, "lod_levels": [], "b4w_proxy_inherit_anim": true, "b4w_selectable": false, "b4w_outlining": false, "b4w_billboard": false, "b4w_pres_glob_orientation": false, "b4w_billboard_geometry": "SPHERICAL", "b4w_outline_settings": {"outline_duration": 1, "outline_period": 1, "outline_relapses": 0}, "b4w_outline_on_select": false, "b4w_use_default_animation": false, "b4w_anim_behavior": "CYCLIC", "b4w_animation_mixing": false, "b4w_shadow_cast_only": false, "b4w_collision": false, "b4w_collision_id": "", "b4w_vehicle": false, "b4w_vehicle_settings": null, "b4w_character": false, "b4w_character_settings": null, "b4w_floating": false, "b4w_floating_settings": null, "pose": null, "field": null, "b4w_correct_bounding_offset": "AUTO", "game": {"physics_type": "STATIC", "use_ghost": false, "use_sleep": false, "mass": 1, "velocity_min": 0, "velocity_max": 0, "damping": 0.04, "rotation_damping": 0.1, "lock_location_x": false, "lock_location_y": false, "lock_location_z": false, "lock_rotation_x": false, "lock_rotation_y": false, "lock_rotation_z": false, "collision_margin": 0.03999999910593033, "collision_group": 1, "collision_mask": 65535, "use_collision_bounds": false, "collision_bounds_type": "BOX", "use_collision_compound": false}, "pass_index": 0, "location": [0, 0, 0], "rotation_quaternion": [1, 0, 0, 0], "scale": [1, 1, 1], "b4w_object_tags": null, "b4w_custom_prop": null, "b4w_anchor": null}, {"name": "Texture+Colorramp", "uuid": "5a9f7e3c3980c825a8d459f2fd0a247e", "type": "MESH", "body_text": null, "data": {"uuid": "d8ea533423df25ae4678f28e9680282e"}, "proxy": null, "dupli_group": null, "parent": null, "b4w_viewport_alignment": null, "pinverse_tsr": null, "parent_type": "OBJECT", "parent_bone": "", "b4w_cluster_data": {"cluster_id": -1, "cluster_center": null, "cluster_radius": 0}, "modifiers": [], "constraints": [], "particle_systems": [], "animation_data": null, "b4w_do_not_batch": false, "b4w_dynamic_geometry": false, "b4w_do_not_cull": false, "b4w_disable_fogging": false, "b4w_do_not_render": false, "b4w_hidden_on_load": false, "b4w_hide_chldr_on_load": false, "b4w_shadow_cast": true, "b4w_shadow_receive": false, "b4w_reflexible": true, "b4w_reflexible_only": false, "b4w_reflective": false, "b4w_reflection_type": "PLANE", "b4w_caustics": false, "b4w_wind_bending": false, "b4w_wind_bending_angle": 10, "b4w_wind_bending_freq": 0.25, "b4w_detail_bending_amp": 0.1, "b4w_detail_bending_freq": 1, "b4w_branch_bending_amp": 0.3, "b4w_main_bend_stiffness_col": "", "b4w_detail_bend_colors": {"leaves_stiffness_col": "", "leaves_phase_col": "", "overall_stiffness_col": ""}, "lod_levels": [], "b4w_proxy_inherit_anim": true, "b4w_selectable": false, "b4w_outlining": false, "b4w_billboard": false, "b4w_pres_glob_orientation": false, "b4w_billboard_geometry": "SPHERICAL", "b4w_outline_settings": {"outline_duration": 1, "outline_period": 1, "outline_relapses": 0}, "b4w_outline_on_select": false, "b4w_use_default_animation": false, "b4w_anim_behavior": "CYCLIC", "b4w_animation_mixing": false, "b4w_shadow_cast_only": false, "b4w_collision": false, "b4w_collision_id": "", "b4w_vehicle": false, "b4w_vehicle_settings": null, "b4w_character": false, "b4w_character_settings": null, "b4w_floating": false, "b4w_floating_settings": null, "pose": null, "field": null, "b4w_correct_bounding_offset": "AUTO", "game": {"physics_type": "STATIC", "use_ghost": false, "use_sleep": false, "mass": 1, "velocity_min": 0, "velocity_max": 0, "damping": 0.04, "rotation_damping": 0.1, "lock_location_x": false, "lock_location_y": false, "lock_location_z": false, "lock_rotation_x": false, "lock_rotation_y": false, "lock_rotation_z": false, "collision_margin": 0.03999999910593033, "collision_group": 1, "collision_mask": 65535, "use_collision_bounds": false, "collision_bounds_type": "BOX", "use_collision_compound": false}, "pass_index": 0, "location": [0.5, 0.5, 0], "rotation_quaternion": [1, 0, 0, 0], "scale": [1, 1, 1], "b4w_object_tags": null, "b4w_custom_prop": null, "b4w_anchor": null}, {"name": "Texture+Colorramp_anotation", "uuid": "45347e3e539e97be8c468a0875fb6c58", "type": "EMPTY", "body_text": null, "data": "", "proxy": null, "dupli_group": null, "parent": {"uuid": "5a9f7e3c3980c825a8d459f2fd0a247e"}, "b4w_viewport_alignment": null, "parent_type": "OBJECT", "parent_bone": "", "b4w_cluster_data": {"cluster_id": -1, "cluster_center": null, "cluster_radius": 0}, "modifiers": [], "constraints": [], "particle_systems": [], "animation_data": null, "b4w_do_not_batch": false, "b4w_dynamic_geometry": false, "b4w_do_not_cull": false, "b4w_disable_fogging": false, "b4w_do_not_render": false, "b4w_hidden_on_load": false, "b4w_hide_chldr_on_load": false, "b4w_shadow_cast": false, "b4w_shadow_receive": false, "b4w_reflexible": false, "b4w_reflexible_only": false, "b4w_reflective": false, "b4w_reflection_type": "PLANE", "b4w_caustics": false, "b4w_wind_bending": false, "b4w_wind_bending_angle": 10, "b4w_wind_bending_freq": 0.25, "b4w_detail_bending_amp": 0.1, "b4w_detail_bending_freq": 1, "b4w_branch_bending_amp": 0.3, "b4w_main_bend_stiffness_col": "", "b4w_detail_bend_colors": {"leaves_stiffness_col": "", "leaves_phase_col": "", "overall_stiffness_col": ""}, "lod_levels": [], "b4w_proxy_inherit_anim": true, "b4w_selectable": false, "b4w_outlining": false, "b4w_billboard": false, "b4w_pres_glob_orientation": false, "b4w_billboard_geometry": "SPHERICAL", "b4w_outline_settings": {"outline_duration": 1, "outline_period": 1, "outline_relapses": 0}, "b4w_outline_on_select": false, "b4w_use_default_animation": false, "b4w_anim_behavior": "CYCLIC", "b4w_animation_mixing": false, "b4w_shadow_cast_only": false, "b4w_collision": false, "b4w_collision_id": "", "b4w_vehicle": false, "b4w_vehicle_settings": null, "b4w_character": false, "b4w_character_settings": null, "b4w_floating": false, "b4w_floating_settings": null, "pose": null, "field": null, "b4w_correct_bounding_offset": "AUTO", "game": {"physics_type": "NO_COLLISION", "use_ghost": false, "use_sleep": false, "mass": 1, "velocity_min": 0, "velocity_max": 0, "damping": 0.04, "rotation_damping": 0.1, "lock_location_x": false, "lock_location_y": false, "lock_location_z": false, "lock_rotation_x": false, "lock_rotation_y": false, "lock_rotation_z": false, "collision_margin": 0.03999999910593033, "collision_group": 1, "collision_mask": 65535, "use_collision_bounds": false, "collision_bounds_type": "BOX", "use_collision_compound": false}, "pass_index": 0, "pinverse_tsr": [-0.73541, -1.19469, 0, 1, 0, 0, 0, 1], "location": [0, 0.03854, 0.93638], "rotation_quaternion": [1, 0, 0, 0], "scale": [1, 1, 1], "b4w_object_tags": {"title": "Color Ramp", "description": "", "category": ""}, "b4w_custom_prop": null, "b4w_anchor": {"type": "ANNOTATION", "detect_visibility": false, "element_id": "", "max_width": 250}}, {"name": "Lamp", "uuid": "1fb063bedfdf73e7feb5774958494d35", "type": "LAMP", "body_text": null, "data": {"uuid": "b601adeb4c589784166684dc99cb5858"}, "proxy": null, "dupli_group": null, "parent": null, "b4w_viewport_alignment": null, "pinverse_tsr": null, "parent_type": "OBJECT", "parent_bone": "", "b4w_cluster_data": {"cluster_id": -1, "cluster_center": null, "cluster_radius": 0}, "modifiers": [], "constraints": [], "particle_systems": [], "animation_data": null, "b4w_do_not_batch": false, "b4w_dynamic_geometry": false, "b4w_do_not_cull": false, "b4w_disable_fogging": false, "b4w_do_not_render": false, "b4w_hidden_on_load": false, "b4w_hide_chldr_on_load": false, "b4w_shadow_cast": false, "b4w_shadow_receive": false, "b4w_reflexible": false, "b4w_reflexible_only": false, "b4w_reflective": false, "b4w_reflection_type": "PLANE", "b4w_caustics": false, "b4w_wind_bending": false, "b4w_wind_bending_angle": 10, "b4w_wind_bending_freq": 0.25, "b4w_detail_bending_amp": 0.1, "b4w_detail_bending_freq": 1, "b4w_branch_bending_amp": 0.3, "b4w_main_bend_stiffness_col": "", "b4w_detail_bend_colors": {"leaves_stiffness_col": "", "leaves_phase_col": "", "overall_stiffness_col": ""}, "lod_levels": [], "b4w_proxy_inherit_anim": true, "b4w_selectable": false, "b4w_outlining": false, "b4w_billboard": false, "b4w_pres_glob_orientation": false, "b4w_billboard_geometry": "SPHERICAL", "b4w_outline_settings": {"outline_duration": 1, "outline_period": 1, "outline_relapses": 0}, "b4w_outline_on_select": false, "b4w_use_default_animation": false, "b4w_anim_behavior": "CYCLIC", "b4w_animation_mixing": false, "b4w_shadow_cast_only": false, "b4w_collision": false, "b4w_collision_id": "", "b4w_vehicle": false, "b4w_vehicle_settings": null, "b4w_character": false, "b4w_character_settings": null, "b4w_floating": false, "b4w_floating_settings": null, "pose": null, "field": null, "b4w_correct_bounding_offset": "AUTO", "game": {"physics_type": "STATIC", "use_ghost": false, "use_sleep": false, "mass": 1, "velocity_min": 0, "velocity_max": 0, "damping": 0.025, "rotation_damping": 0.159, "lock_location_x": false, "lock_location_y": false, "lock_location_z": false, "lock_rotation_x": false, "lock_rotation_y": false, "lock_rotation_z": false, "collision_margin": 0.05999999865889549, "collision_group": 1, "collision_mask": 255, "use_collision_bounds": false, "collision_bounds_type": "BOX", "use_collision_compound": false}, "pass_index": 0, "location": [-1.00545, 4.07625, 5.90386], "rotation_quaternion": [-0.13077, -0.0729, 0.31201, 0.93821], "scale": [1, 1, 1], "b4w_object_tags": null, "b4w_custom_prop": null, "b4w_anchor": null}, {"name": "Camera", "uuid": "bb5482b1784ac45234e2a673c00abb77", "type": "CAMERA", "body_text": null, "data": {"uuid": "b6795846bc31d65d265ab395507bf8fb"}, "proxy": null, "dupli_group": null, "parent": null, "b4w_viewport_alignment": null, "pinverse_tsr": null, "parent_type": "OBJECT", "parent_bone": "", "b4w_cluster_data": {"cluster_id": -1, "cluster_center": null, "cluster_radius": 0}, "modifiers": [], "constraints": [], "particle_systems": [], "animation_data": null, "b4w_do_not_batch": false, "b4w_dynamic_geometry": false, "b4w_do_not_cull": false, "b4w_disable_fogging": false, "b4w_do_not_render": false, "b4w_hidden_on_load": false, "b4w_hide_chldr_on_load": false, "b4w_shadow_cast": false, "b4w_shadow_receive": false, "b4w_reflexible": false, "b4w_reflexible_only": false, "b4w_reflective": false, "b4w_reflection_type": "PLANE", "b4w_caustics": false, "b4w_wind_bending": false, "b4w_wind_bending_angle": 10, "b4w_wind_bending_freq": 0.25, "b4w_detail_bending_amp": 0.1, "b4w_detail_bending_freq": 1, "b4w_branch_bending_amp": 0.3, "b4w_main_bend_stiffness_col": "", "b4w_detail_bend_colors": {"leaves_stiffness_col": "", "leaves_phase_col": "", "overall_stiffness_col": ""}, "lod_levels": [], "b4w_proxy_inherit_anim": true, "b4w_selectable": false, "b4w_outlining": false, "b4w_billboard": false, "b4w_pres_glob_orientation": false, "b4w_billboard_geometry": "SPHERICAL", "b4w_outline_settings": {"outline_duration": 1, "outline_period": 1, "outline_relapses": 0}, "b4w_outline_on_select": false, "b4w_use_default_animation": false, "b4w_anim_behavior": "CYCLIC", "b4w_animation_mixing": false, "b4w_shadow_cast_only": false, "b4w_collision": false, "b4w_collision_id": "", "b4w_vehicle": false, "b4w_vehicle_settings": null, "b4w_character": false, "b4w_character_settings": null, "b4w_floating": false, "b4w_floating_settings": null, "pose": null, "field": null, "b4w_correct_bounding_offset": "AUTO", "game": {"physics_type": "STATIC", "use_ghost": false, "use_sleep": false, "mass": 1, "velocity_min": 0, "velocity_max": 0, "damping": 0.566, "rotation_damping": 0.626, "lock_location_x": false, "lock_location_y": false, "lock_location_z": false, "lock_rotation_x": false, "lock_rotation_y": false, "lock_rotation_z": false, "collision_margin": 0.05999999865889549, "collision_group": 1, "collision_mask": 255, "use_collision_bounds": false, "collision_bounds_type": "BOX", "use_collision_compound": false}, "pass_index": 0, "location": [0.00261, 4.13143, 1.19331], "rotation_quaternion": [0.00028, 0.00023, 0.62713, 0.77892], "scale": [1, 1, 1], "b4w_object_tags": null, "b4w_custom_prop": null, "b4w_anchor": null}], "groups": [], "scenes": [{"name": "Scene", "uuid": "b337c11cdc346168b4f15f080a28a9fa", "b4w_use_nla": false, "b4w_nla_cyclic": false, "b4w_logic_nodes": [], "b4w_use_logic_editor": false, "b4w_enable_dynamic_compressor": false, "b4w_dynamic_compressor_settings": {"threshold": -24, "knee": 30, "ratio": 12, "attack": 0.003, "release": 0.25}, "b4w_shadow_settings": {"csm_resolution": 2048, "blur_samples": "16x", "soft_shadows": true, "self_shadow_polygon_offset": 1, "self_shadow_normal_offset": 0.01, "b4w_enable_csm": false, "csm_num": 1, "csm_first_cascade_border": 10, "first_cascade_blur_radius": 3, "csm_last_cascade_border": 100, "last_cascade_blur_radius": 1.5, "fade_last_cascade": true, "blend_between_cascades": true}, "b4w_god_rays_settings": {"intensity": 0.7, "max_ray_length": 1, "steps_per_pass": 10}, "b4w_ssao_settings": {"radius_increase": 3, "hemisphere": false, "blur_depth": false, "blur_discard_value": 1, "influence": 0.7, "dist_factor": 0, "samples": 16}, "b4w_color_correction_settings": {"brightness": 0, "contrast": 0, "exposure": 1, "saturation": 1}, "b4w_bloom_settings": {"key": 1, "blur": 4, "edge_lum": 1, "adaptive": true, "average_luminance": 0.5}, "b4w_motion_blur_settings": {"motion_blur_factor": 0.01, "motion_blur_decay_threshold": 0.01}, "b4w_glow_settings": {"render_glow_over_blend": false, "small_glow_mask_coeff": 2, "large_glow_mask_coeff": 2, "small_glow_mask_width": 2, "large_glow_mask_width": 6}, "b4w_outline_color": [1, 1, 1], "b4w_outline_factor": 1, "b4w_enable_physics": "AUTO", "b4w_render_shadows": "AUTO", "b4w_render_reflections": "ON", "b4w_reflection_quality": "HIGH", "b4w_render_refractions": "AUTO", "b4w_render_dynamic_grass": "AUTO", "b4w_enable_god_rays": false, "b4w_enable_glow_materials": "AUTO", "b4w_enable_ssao": false, "b4w_batch_grid_size": 0, "b4w_anisotropic_filtering": "16x", "b4w_enable_bloom": false, "b4w_enable_motion_blur": false, "b4w_enable_color_correction": false, "b4w_antialiasing_quality": "MEDIUM", "b4w_enable_object_selection": "AUTO", "b4w_enable_outlining": "AUTO", "b4w_enable_anchors_visibility": "AUTO", "b4w_lod_smooth_type": "NON-OPAQUE", "b4w_lod_hyst_interval": 4.0, "b4w_tags": null, "b4w_custom_prop": null, "objects": [{"uuid": "1d0a925e7df29d95b7af567511ed015f"}, {"uuid": "f2b1b87f4e97a656433d5c0a80d7bfde"}, {"uuid": "0fc3dd6ef23f207da411726f0182a458"}, {"uuid": "5a9f7e3c3980c825a8d459f2fd0a247e"}, {"uuid": "45347e3e539e97be8c468a0875fb6c58"}, {"uuid": "1fb063bedfdf73e7feb5774958494d35"}, {"uuid": "bb5482b1784ac45234e2a673c00abb77"}], "camera": {"uuid": "bb5482b1784ac45234e2a673c00abb77"}, "world": {"uuid": "be945a8f53d9252de56bd6ec28a90e05"}, "frame_start": 1, "frame_end": 250, "timeline_markers": null, "fps": 24, "audio_volume": 1, "audio_doppler_speed": 343.3, "audio_doppler_factor": 1, "audio_distance_model": "INVERSE_CLAMPED"}], "worlds": [{"name": "World", "uuid": "be945a8f53d9252de56bd6ec28a90e05", "texture_slots": [], "use_orco_tex_coord": false, "horizon_color": [0.6, 0.6, 0.6], "zenith_color": [0.01, 0.01, 0.01], "use_sky_paper": false, "use_sky_blend": false, "use_sky_real": false, "b4w_use_default_animation": false, "b4w_anim_behavior": "CYCLIC", "use_nodes": false, "uv_vc_key": "", "light_settings": {"use_environment_light": true, "environment_energy": 0.4, "environment_color": "PLAIN"}, "b4w_sky_settings": {"render_sky": true, "reflexible": true, "reflexible_only": false, "procedural_skydome": false, "use_as_environment_lighting": false, "color": [0.087, 0.255, 0.6], "rayleigh_brightness": 3.3, "mie_brightness": 0.1, "spot_brightness": 20, "scatter_strength": 0.2, "rayleigh_strength": 0.2, "mie_strength": 0.006, "rayleigh_collection_power": 0.35, "mie_collection_power": 0.5, "mie_distribution": 0.4}, "fog_settings": {"use_fog": false, "intensity": 0, "depth": 25, "start": 5, "height": 0, "falloff": "QUADRATIC", "use_custom_color": false, "color": [0.5, 0.5, 0.5]}, "animation_data": null, "node_tree": null}], "node_groups": [{"name": "B4W_SMOOTHSTEP.001", "use_orco_tex_coord": false, "uv_vc_key": "", "uuid": "8b173179470c3e9517d954135c27f412", "node_tree": {"nodes": [{"name": "Math.006", "type": "MATH", "operation": "SUBTRACT", "use_clamp": false, "inputs": [{"name": "Value", "identifier": "Value", "is_linked": true, "default_value": 3}, {"name": "Value", "identifier": "Value_001", "is_linked": true, "default_value": 2}], "outputs": [{"name": "Value", "identifier": "Value", "is_linked": true, "default_value": 0}]}, {"name": "Math.008", "type": "MATH", "operation": "DIVIDE", "use_clamp": false, "inputs": [{"name": "Value", "identifier": "Value", "is_linked": true, "default_value": 3}, {"name": "Value", "identifier": "Value_001", "is_linked": true, "default_value": 2}], "outputs": [{"name": "Value", "identifier": "Value", "is_linked": true, "default_value": 0}]}, {"name": "Group Input", "type": "GROUP_INPUT", "inputs": [], "outputs": [{"name": "Value", "identifier": "Input_1", "is_linked": true, "default_value": 0.5}, {"name": "Edge0", "identifier": "Input_5", "is_linked": true, "default_value": 2}, {"name": "Edge1", "identifier": "Input_7", "is_linked": true, "default_value": 3}]}, {"name": "Math.005", "type": "MATH", "operation": "SUBTRACT", "use_clamp": false, "inputs": [{"name": "Value", "identifier": "Value", "is_linked": false, "default_value": 3}, {"name": "Value", "identifier": "Value_001", "is_linked": true, "default_value": 2}], "outputs": [{"name": "Value", "identifier": "Value", "is_linked": true, "default_value": 0}]}, {"name": "Math.007", "type": "MATH", "operation": "SUBTRACT", "use_clamp": false, "inputs": [{"name": "Value", "identifier": "Value", "is_linked": true, "default_value": 3}, {"name": "Value", "identifier": "Value_001", "is_linked": true, "default_value": 2}], "outputs": [{"name": "Value", "identifier": "Value", "is_linked": true, "default_value": 0}]}, {"name": "Math.001", "type": "MATH", "operation": "MAXIMUM", "use_clamp": false, "inputs": [{"name": "Value", "identifier": "Value", "is_linked": true, "default_value": 1}, {"name": "Value", "identifier": "Value_001", "is_linked": false, "default_value": 0}], "outputs": [{"name": "Value", "identifier": "Value", "is_linked": true, "default_value": 0}]}, {"name": "Math.002", "type": "MATH", "operation": "MULTIPLY", "use_clamp": false, "inputs": [{"name": "Value", "identifier": "Value", "is_linked": true, "default_value": 0.5}, {"name": "Value", "identifier": "Value_001", "is_linked": true, "default_value": 0.5}], "outputs": [{"name": "Value", "identifier": "Value", "is_linked": true, "default_value": 0}]}, {"name": "Math.003", "type": "MATH", "operation": "MULTIPLY", "use_clamp": false, "inputs": [{"name": "Value", "identifier": "Value", "is_linked": true, "default_value": 0.5}, {"name": "Value", "identifier": "Value_001", "is_linked": true, "default_value": 0.5}], "outputs": [{"name": "Value", "identifier": "Value", "is_linked": true, "default_value": 0}]}, {"name": "Group Output", "type": "GROUP_OUTPUT", "inputs": [{"name": "Value", "identifier": "Output_3", "is_linked": true, "default_value": 0}], "outputs": []}, {"name": "Math.004", "type": "MATH", "operation": "MULTIPLY", "use_clamp": false, "inputs": [{"name": "Value", "identifier": "Value", "is_linked": true, "default_value": 0.5}, {"name": "Value", "identifier": "Value_001", "is_linked": false, "default_value": 2}], "outputs": [{"name": "Value", "identifier": "Value", "is_linked": true, "default_value": 0}]}, {"name": "Math", "type": "MATH", "operation": "MINIMUM", "use_clamp": false, "inputs": [{"name": "Value", "identifier": "Value", "is_linked": true, "default_value": 0.5}, {"name": "Value", "identifier": "Value_001", "is_linked": false, "default_value": 1}], "outputs": [{"name": "Value", "identifier": "Value", "is_linked": true, "default_value": 0}]}], "links": [{"from_node": {"name": "Math.001"}, "to_node": {"name": "Math.002"}, "from_socket": {"identifier": "Value"}, "to_socket": {"identifier": "Value"}}, {"from_node": {"name": "Math.001"}, "to_node": {"name": "Math.002"}, "from_socket": {"identifier": "Value"}, "to_socket": {"identifier": "Value_001"}}, {"from_node": {"name": "Math.002"}, "to_node": {"name": "Math.003"}, "from_socket": {"identifier": "Value"}, "to_socket": {"identifier": "Value"}}, {"from_node": {"name": "Math.003"}, "to_node": {"name": "Group Output"}, "from_socket": {"identifier": "Value"}, "to_socket": {"identifier": "Output_3"}}, {"from_node": {"name": "Math.001"}, "to_node": {"name": "Math.004"}, "from_socket": {"identifier": "Value"}, "to_socket": {"identifier": "Value"}}, {"from_node": {"name": "Math.004"}, "to_node": {"name": "Math.005"}, "from_socket": {"identifier": "Value"}, "to_socket": {"identifier": "Value_001"}}, {"from_node": {"name": "Math.005"}, "to_node": {"name": "Math.003"}, "from_socket": {"identifier": "Value"}, "to_socket": {"identifier": "Value_001"}}, {"from_node": {"name": "Group Input"}, "to_node": {"name": "Math.006"}, "from_socket": {"identifier": "Input_1"}, "to_socket": {"identifier": "Value"}}, {"from_node": {"name": "Group Input"}, "to_node": {"name": "Math.006"}, "from_socket": {"identifier": "Input_5"}, "to_socket": {"identifier": "Value_001"}}, {"from_node": {"name": "Group Input"}, "to_node": {"name": "Math.007"}, "from_socket": {"identifier": "Input_7"}, "to_socket": {"identifier": "Value"}}, {"from_node": {"name": "Group Input"}, "to_node": {"name": "Math.007"}, "from_socket": {"identifier": "Input_5"}, "to_socket": {"identifier": "Value_001"}}, {"from_node": {"name": "Math.006"}, "to_node": {"name": "Math.008"}, "from_socket": {"identifier": "Value"}, "to_socket": {"identifier": "Value"}}, {"from_node": {"name": "Math.007"}, "to_node": {"name": "Math.008"}, "from_socket": {"identifier": "Value"}, "to_socket": {"identifier": "Value_001"}}, {"from_node": {"name": "Math.008"}, "to_node": {"name": "Math"}, "from_socket": {"identifier": "Value"}, "to_socket": {"identifier": "Value"}}, {"from_node": {"name": "Math"}, "to_node": {"name": "Math.001"}, "from_socket": {"identifier": "Value"}, "to_socket": {"identifier": "Value"}}], "animation_data": null}}], "binaries": [{"binfile": "ramps.bin", "int": 0, "float": 206328, "short": 478000, "ushort": 662372, "uchar": 662372}], "b4w_export_warnings": [], "b4w_export_errors": []}