{"b4w_format_version": "6.01", "b4w_filepath_blend": "../../../blender/particles/billboard_tilt.blend", "actions": [], "images": [{"name": "logo_white_image_only.png", "uuid": "42a8aafd0aca3d383a46455a8fcc1bd8", "filepath": "billboard_tilt.png", "size": [1024, 1024], "source": "FILE", "colorspace_settings_name": "sRGB"}], "textures": [{"name": "Texture", "uuid": "285e3c72abafe1510bc9b0b92eb4427a", "type": "IMAGE", "b4w_source_type": "NONE", "b4w_source_id": "", "b4w_source_size": "128", "b4w_enable_canvas_mipmapping": true, "extension": "REPEAT", "b4w_use_map_parallax": false, "b4w_parallax_scale": 0.02, "b4w_parallax_steps": 5, "b4w_parallax_lod_dist": 5, "b4w_water_foam": false, "b4w_foam_uv_freq": [1, 1], "b4w_foam_uv_magnitude": [1, 1], "b4w_shore_dist_map": false, "b4w_anisotropic_filtering": "DEFAULT", "b4w_shore_boundings": [0, 0, 0, 0], "b4w_max_shore_dist": 100, "b4w_disable_compression": false, "b4w_use_as_skydome": true, "b4w_use_as_environment_lighting": false, "image": {"uuid": "42a8aafd0aca3d383a46455a8fcc1bd8"}, "frame_duration": 0, "frame_offset": 0, "frame_start": 0, "use_auto_refresh": false, "use_cyclic": false, "movie_length": 0, "b4w_nla_video": false, "noise_intensity": null, "noise_scale": null, "use_color_ramp": false, "color_ramp": null}, {"name": "Texture.001", "uuid": "257c8e7ed183b18ab2676c3bdbeb9a9a", "type": "BLEND", "b4w_source_type": "NONE", "b4w_source_id": "", "b4w_source_size": "128", "b4w_enable_canvas_mipmapping": true, "extension": null, "b4w_use_map_parallax": false, "b4w_parallax_scale": 0.02, "b4w_parallax_steps": 5, "b4w_parallax_lod_dist": 5, "b4w_water_foam": false, "b4w_foam_uv_freq": [1, 1], "b4w_foam_uv_magnitude": [1, 1], "b4w_shore_dist_map": false, "b4w_anisotropic_filtering": "DEFAULT", "b4w_shore_boundings": [0, 0, 0, 0], "b4w_max_shore_dist": 100, "b4w_disable_compression": false, "b4w_use_as_skydome": true, "b4w_use_as_environment_lighting": false, "image": null, "frame_duration": 0, "frame_offset": 0, "frame_start": 0, "use_auto_refresh": false, "use_cyclic": false, "movie_length": 0, "b4w_nla_video": false, "noise_intensity": null, "noise_scale": null, "use_color_ramp": true, "color_ramp": {"elements": [{"position": 0, "color": [1, 1, 1, 1]}, {"position": 0.529, "color": [0, 0, 0, 1]}]}}], "materials": [{"use_orco_tex_coord": false, "name": "Material", "use_nodes": true, "diffuse_color": [0.8, 0.8, 0.8], "diffuse_shader": "LAMBERT", "roughness": 0.5, "diffuse_fresnel": 0.1, "diffuse_fresnel_factor": 0.5, "darkness": 1, "diffuse_toon_size": 0.5, "diffuse_toon_smooth": 0.1, "diffuse_intensity": 0.8, "alpha": 1, "specular_alpha": 1, "raytrace_transparency": {"fresnel": 0, "fresnel_factor": 1.25}, "raytrace_mirror": {"reflect_factor": 0, "fresnel": 0, "fresnel_factor": 1.25}, "specular_color": [1, 1, 1], "specular_intensity": 0.5, "specular_shader": "COOKTORR", "specular_hardness": 50, "specular_ior": 4, "specular_slope": 0.1, "specular_toon_size": 0.5, "specular_toon_smooth": 0.1, "emit": 0, "ambient": 1, "use_vertex_color_paint": false, "b4w_water": false, "b4w_water_shore_smoothing": true, "b4w_water_absorb_factor": 6, "b4w_water_dynamic": false, "b4w_waves_height": 1, "b4w_waves_length": 10, "b4w_generated_mesh": false, "b4w_water_num_cascads": 5, "b4w_water_subdivs": 64, "b4w_water_detailed_dist": 1000, "b4w_water_fog_color": [0.4, 0.6, 0.7], "b4w_water_fog_density": 0.06, "b4w_foam_factor": 0.5, "b4w_shallow_water_col": [0, 0.8, 0.3], "b4w_shore_water_col": [0, 0.9, 0.2], "b4w_shallow_water_col_fac": 1, "b4w_shore_water_col_fac": 0.5, "b4w_water_dst_noise_scale0": 0.05, "b4w_water_dst_noise_scale1": 0.03, "b4w_water_dst_noise_freq0": 1.3, "b4w_water_dst_noise_freq1": 1, "b4w_water_dir_min_shore_fac": 0.4, "b4w_water_dir_freq": 0.5, "b4w_water_dir_noise_scale": 0.05, "b4w_water_dir_noise_freq": 0.07, "b4w_water_dir_min_noise_fac": 0.5, "b4w_water_dst_min_fac": 0.2, "b4w_water_waves_hor_fac": 5, "b4w_water_sss_strength": 1, "b4w_water_sss_width": 0.45, "b4w_water_norm_uv_velocity": 0.05, "b4w_water_enable_caust": false, "b4w_water_caust_scale": 0.25, "b4w_water_caust_brightness": 0.5, "b4w_terrain": false, "b4w_dynamic_grass_size": "", "b4w_dynamic_grass_color": "", "b4w_do_not_render": false, "b4w_lens_flares": false, "b4w_collision": false, "b4w_use_ghost": false, "b4w_collision_id": "", "b4w_collision_margin": 0.03999999910593033, "b4w_collision_group": 128, "b4w_collision_mask": 65407, "b4w_double_sided_lighting": false, "b4w_wettable": false, "b4w_refractive": false, "b4w_refr_bump": 0.0010000000474974513, "b4w_render_above_all": false, "physics": {"friction": 0.5, "elasticity": 0}, "type": "SURFACE", "b4w_halo_sky_stars": false, "b4w_halo_stars_blend_height": 10.0, "b4w_halo_stars_min_height": 0.0, "halo": {"hardness": 50, "size": 0.5, "b4w_halo_rings_color": [1, 1, 1], "b4w_halo_lines_color": [1, 1, 1], "ring_count": 0, "line_count": 0, "star_tip_count": 0}, "use_transparency": false, "use_shadeless": false, "use_tangent_shading": false, "offset_z": 0, "game_settings": {"alpha_blend": "ADD", "use_backface_culling": true}, "uv_vc_key": "UVMap", "node_tree": {"nodes": [{"name": "Texture", "type": "TEXTURE", "inputs": [{"name": "Vector", "identifier": "Vector", "is_linked": true, "default_value": [0, 0, 0]}], "outputs": [{"name": "Value", "identifier": "Value", "is_linked": true, "default_value": 0}, {"name": "Color", "identifier": "Color", "is_linked": true, "default_value": [0, 0, 0, 0]}, {"name": "Normal", "identifier": "Normal", "is_linked": false, "default_value": [0, 0, 0]}], "texture": {"uuid": "285e3c72abafe1510bc9b0b92eb4427a"}}, {"name": "Geometry", "type": "GEOMETRY", "inputs": [], "outputs": [{"name": "Global", "identifier": "Global", "is_linked": false, "default_value": [0, 0, 0]}, {"name": "Local", "identifier": "Local", "is_linked": false, "default_value": [0, 0, 0]}, {"name": "View", "identifier": "View", "is_linked": false, "default_value": [0, 0, 0]}, {"name": "Orco", "identifier": "Orco", "is_linked": false, "default_value": [0, 0, 0]}, {"name": "UV", "identifier": "UV", "is_linked": true, "default_value": [0, 0, 0]}, {"name": "Normal", "identifier": "Normal", "is_linked": false, "default_value": [0, 0, 0]}, {"name": "Vertex Color", "identifier": "Vertex Color", "is_linked": false, "default_value": [0, 0, 0, 0]}, {"name": "Vertex Alpha", "identifier": "Vertex Alpha", "is_linked": false, "default_value": 0}, {"name": "Front/Back", "identifier": "Front/Back", "is_linked": false, "default_value": 0}], "uv_layer": "UVMap", "color_layer": ""}, {"name": "Output", "type": "OUTPUT", "inputs": [{"name": "Color", "identifier": "Color", "is_linked": true, "default_value": [0, 0, 0, 1]}, {"name": "Alpha", "identifier": "Alpha", "is_linked": true, "default_value": 1}], "outputs": []}], "links": [{"from_node": {"name": "Texture"}, "to_node": {"name": "Output"}, "from_socket": {"identifier": "Color"}, "to_socket": {"identifier": "Color"}}, {"from_node": {"name": "Geometry"}, "to_node": {"name": "Texture"}, "from_socket": {"identifier": "UV"}, "to_socket": {"identifier": "Vector"}}, {"from_node": {"name": "Texture"}, "to_node": {"name": "Output"}, "from_socket": {"identifier": "Value"}, "to_socket": {"identifier": "Alpha"}}], "animation_data": null}, "texture_slots": [], "uuid": "764864695a36734c3b2f0e9f337bfa20", "source_uuid": "e3c586abe61624785244c5fbfd6931fb"}, {"use_orco_tex_coord": false, "name": "Material.001", "use_nodes": false, "diffuse_color": [0.162, 0.3185, 0.5333], "diffuse_shader": "LAMBERT", "roughness": 0.5, "diffuse_fresnel": 0.1, "diffuse_fresnel_factor": 0.5, "darkness": 1, "diffuse_toon_size": 0.5, "diffuse_toon_smooth": 0.1, "diffuse_intensity": 0.8, "alpha": 1, "specular_alpha": 1, "raytrace_transparency": {"fresnel": 0, "fresnel_factor": 1.25}, "raytrace_mirror": {"reflect_factor": 0, "fresnel": 0, "fresnel_factor": 1.25}, "specular_color": [0.1697, 0.6622, 1], "specular_intensity": 0.5, "specular_shader": "COOKTORR", "specular_hardness": 96, "specular_ior": 4, "specular_slope": 0.1, "specular_toon_size": 0.5, "specular_toon_smooth": 0.1, "emit": 0, "ambient": 1, "use_vertex_color_paint": false, "b4w_water": false, "b4w_water_shore_smoothing": true, "b4w_water_absorb_factor": 6, "b4w_water_dynamic": false, "b4w_waves_height": 1, "b4w_waves_length": 10, "b4w_generated_mesh": false, "b4w_water_num_cascads": 5, "b4w_water_subdivs": 64, "b4w_water_detailed_dist": 1000, "b4w_water_fog_color": [0.4, 0.6, 0.7], "b4w_water_fog_density": 0.06, "b4w_foam_factor": 0.5, "b4w_shallow_water_col": [0, 0.8, 0.3], "b4w_shore_water_col": [0, 0.9, 0.2], "b4w_shallow_water_col_fac": 1, "b4w_shore_water_col_fac": 0.5, "b4w_water_dst_noise_scale0": 0.05, "b4w_water_dst_noise_scale1": 0.03, "b4w_water_dst_noise_freq0": 1.3, "b4w_water_dst_noise_freq1": 1, "b4w_water_dir_min_shore_fac": 0.4, "b4w_water_dir_freq": 0.5, "b4w_water_dir_noise_scale": 0.05, "b4w_water_dir_noise_freq": 0.07, "b4w_water_dir_min_noise_fac": 0.5, "b4w_water_dst_min_fac": 0.2, "b4w_water_waves_hor_fac": 5, "b4w_water_sss_strength": 1, "b4w_water_sss_width": 0.45, "b4w_water_norm_uv_velocity": 0.05, "b4w_water_enable_caust": false, "b4w_water_caust_scale": 0.25, "b4w_water_caust_brightness": 0.5, "b4w_terrain": false, "b4w_dynamic_grass_size": "", "b4w_dynamic_grass_color": "", "b4w_do_not_render": false, "b4w_lens_flares": false, "b4w_collision": false, "b4w_use_ghost": false, "b4w_collision_id": "", "b4w_collision_margin": 0.03999999910593033, "b4w_collision_group": 128, "b4w_collision_mask": 65407, "b4w_double_sided_lighting": false, "b4w_wettable": false, "b4w_refractive": false, "b4w_refr_bump": 0.0010000000474974513, "b4w_render_above_all": false, "physics": {"friction": 0.5, "elasticity": 0}, "type": "SURFACE", "b4w_halo_sky_stars": false, "b4w_halo_stars_blend_height": 10.0, "b4w_halo_stars_min_height": 0.0, "halo": {"hardness": 96, "size": 0.5, "b4w_halo_rings_color": [1, 1, 1], "b4w_halo_lines_color": [0.1697, 0.6622, 1], "ring_count": 0, "line_count": 0, "star_tip_count": 0}, "use_transparency": false, "use_shadeless": false, "use_tangent_shading": false, "offset_z": 0, "game_settings": {"alpha_blend": "OPAQUE", "use_backface_culling": true}, "uv_vc_key": "", "node_tree": null, "texture_slots": [], "uuid": "28040b64f558e7f6adc9fff373575f54", "source_uuid": "28040b64f558e7f6adc9fff373575f54"}, {"use_orco_tex_coord": false, "name": "Material.002", "use_nodes": false, "diffuse_color": [0.2899, 0.5871, 1], "diffuse_shader": "LAMBERT", "roughness": 0.5, "diffuse_fresnel": 0.1, "diffuse_fresnel_factor": 0.5, "darkness": 1, "diffuse_toon_size": 0.5, "diffuse_toon_smooth": 0.1, "diffuse_intensity": 0.8, "alpha": 1, "specular_alpha": 1, "raytrace_transparency": {"fresnel": 0, "fresnel_factor": 1.25}, "raytrace_mirror": {"reflect_factor": 0, "fresnel": 0, "fresnel_factor": 1.25}, "specular_color": [0.1697, 0.6622, 1], "specular_intensity": 0.5, "specular_shader": "COOKTORR", "specular_hardness": 96, "specular_ior": 4, "specular_slope": 0.1, "specular_toon_size": 0.5, "specular_toon_smooth": 0.1, "emit": 0.4, "ambient": 1, "use_vertex_color_paint": false, "b4w_water": false, "b4w_water_shore_smoothing": true, "b4w_water_absorb_factor": 6, "b4w_water_dynamic": false, "b4w_waves_height": 1, "b4w_waves_length": 10, "b4w_generated_mesh": false, "b4w_water_num_cascads": 5, "b4w_water_subdivs": 64, "b4w_water_detailed_dist": 1000, "b4w_water_fog_color": [0.4, 0.6, 0.7], "b4w_water_fog_density": 0.06, "b4w_foam_factor": 0.5, "b4w_shallow_water_col": [0, 0.8, 0.3], "b4w_shore_water_col": [0, 0.9, 0.2], "b4w_shallow_water_col_fac": 1, "b4w_shore_water_col_fac": 0.5, "b4w_water_dst_noise_scale0": 0.05, "b4w_water_dst_noise_scale1": 0.03, "b4w_water_dst_noise_freq0": 1.3, "b4w_water_dst_noise_freq1": 1, "b4w_water_dir_min_shore_fac": 0.4, "b4w_water_dir_freq": 0.5, "b4w_water_dir_noise_scale": 0.05, "b4w_water_dir_noise_freq": 0.07, "b4w_water_dir_min_noise_fac": 0.5, "b4w_water_dst_min_fac": 0.2, "b4w_water_waves_hor_fac": 5, "b4w_water_sss_strength": 1, "b4w_water_sss_width": 0.45, "b4w_water_norm_uv_velocity": 0.05, "b4w_water_enable_caust": false, "b4w_water_caust_scale": 0.25, "b4w_water_caust_brightness": 0.5, "b4w_terrain": false, "b4w_dynamic_grass_size": "", "b4w_dynamic_grass_color": "", "b4w_do_not_render": false, "b4w_lens_flares": false, "b4w_collision": false, "b4w_use_ghost": false, "b4w_collision_id": "", "b4w_collision_margin": 0.03999999910593033, "b4w_collision_group": 128, "b4w_collision_mask": 65407, "b4w_double_sided_lighting": false, "b4w_wettable": false, "b4w_refractive": false, "b4w_refr_bump": 0.0010000000474974513, "b4w_render_above_all": false, "physics": {"friction": 0.5, "elasticity": 0}, "type": "SURFACE", "b4w_halo_sky_stars": false, "b4w_halo_stars_blend_height": 10.0, "b4w_halo_stars_min_height": 0.0, "halo": {"hardness": 96, "size": 0.5, "b4w_halo_rings_color": [1, 1, 1], "b4w_halo_lines_color": [0.1697, 0.6622, 1], "ring_count": 0, "line_count": 0, "star_tip_count": 0}, "use_transparency": false, "use_shadeless": false, "use_tangent_shading": false, "offset_z": 0, "game_settings": {"alpha_blend": "OPAQUE", "use_backface_culling": true}, "uv_vc_key": "", "node_tree": null, "texture_slots": [], "uuid": "693050a9303c88ff2328f1150d1afc0c", "source_uuid": "693050a9303c88ff2328f1150d1afc0c"}, {"use_orco_tex_coord": false, "name": "Material.003", "use_nodes": false, "diffuse_color": [0.1527, 0.1681, 0.2968], "diffuse_shader": "LAMBERT", "roughness": 0.5, "diffuse_fresnel": 0.1, "diffuse_fresnel_factor": 0.5, "darkness": 1, "diffuse_toon_size": 0.5, "diffuse_toon_smooth": 0.1, "diffuse_intensity": 1, "alpha": 1, "specular_alpha": 1, "raytrace_transparency": {"fresnel": 0, "fresnel_factor": 1.25}, "raytrace_mirror": {"reflect_factor": 1, "fresnel": 0, "fresnel_factor": 1.25}, "specular_color": [1, 1, 1], "specular_intensity": 0.1012, "specular_shader": "COOKTORR", "specular_hardness": 19, "specular_ior": 4, "specular_slope": 0.1, "specular_toon_size": 0.5, "specular_toon_smooth": 0.1, "emit": 0, "ambient": 1, "use_vertex_color_paint": false, "b4w_water": false, "b4w_water_shore_smoothing": true, "b4w_water_absorb_factor": 6, "b4w_water_dynamic": false, "b4w_waves_height": 1, "b4w_waves_length": 10, "b4w_generated_mesh": false, "b4w_water_num_cascads": 5, "b4w_water_subdivs": 64, "b4w_water_detailed_dist": 1000, "b4w_water_fog_color": [0.4, 0.6, 0.7], "b4w_water_fog_density": 0.06, "b4w_foam_factor": 0.5, "b4w_shallow_water_col": [0, 0.8, 0.3], "b4w_shore_water_col": [0, 0.9, 0.2], "b4w_shallow_water_col_fac": 1, "b4w_shore_water_col_fac": 0.5, "b4w_water_dst_noise_scale0": 0.05, "b4w_water_dst_noise_scale1": 0.03, "b4w_water_dst_noise_freq0": 1.3, "b4w_water_dst_noise_freq1": 1, "b4w_water_dir_min_shore_fac": 0.4, "b4w_water_dir_freq": 0.5, "b4w_water_dir_noise_scale": 0.05, "b4w_water_dir_noise_freq": 0.07, "b4w_water_dir_min_noise_fac": 0.5, "b4w_water_dst_min_fac": 0.2, "b4w_water_waves_hor_fac": 5, "b4w_water_sss_strength": 1, "b4w_water_sss_width": 0.45, "b4w_water_norm_uv_velocity": 0.05, "b4w_water_enable_caust": false, "b4w_water_caust_scale": 0.25, "b4w_water_caust_brightness": 0.5, "b4w_terrain": false, "b4w_dynamic_grass_size": "", "b4w_dynamic_grass_color": "", "b4w_do_not_render": false, "b4w_lens_flares": false, "b4w_collision": false, "b4w_use_ghost": false, "b4w_collision_id": "", "b4w_collision_margin": 0.03999999910593033, "b4w_collision_group": 128, "b4w_collision_mask": 65407, "b4w_double_sided_lighting": false, "b4w_wettable": false, "b4w_refractive": false, "b4w_refr_bump": 0.0010000000474974513, "b4w_render_above_all": false, "physics": {"friction": 0.5, "elasticity": 0}, "type": "SURFACE", "b4w_halo_sky_stars": false, "b4w_halo_stars_blend_height": 10.0, "b4w_halo_stars_min_height": 0.0, "halo": {"hardness": 19, "size": 0.5, "b4w_halo_rings_color": [1, 1, 1], "b4w_halo_lines_color": [1, 1, 1], "ring_count": 0, "line_count": 0, "star_tip_count": 0}, "use_transparency": false, "use_shadeless": false, "use_tangent_shading": false, "offset_z": 0, "game_settings": {"alpha_blend": "OPAQUE", "use_backface_culling": true}, "uv_vc_key": "", "node_tree": null, "texture_slots": [], "uuid": "e24cefb9809b42dd5a871719f7b6acf6", "source_uuid": "e24cefb9809b42dd5a871719f7b6acf6"}], "meshes": [{"name": "Cube.000_MODIFIERS_APPLIED", "uuid": "fea8b50337660af2f9e5c1f224794f91", "materials": [{"uuid": "764864695a36734c3b2f0e9f337bfa20"}, {"uuid": "28040b64f558e7f6adc9fff373575f54"}], "b4w_vertex_anim": [], "vertex_groups": [], "uv_textures": ["UVMap"], "active_vcol_name": "Col", "submeshes": [{"boundings": {"bb": {"max_x": 0, "max_y": 0, "max_z": 0, "min_x": 0, "min_y": 0, "min_z": 0}, "be_ax": [0, 0, 0], "be_cen": [0, 0, 0], "rbb": {"rbb_c": [0.0, 0.0, 0.0], "rbb_s": [0.0, 0.0, 0.0]}, "caxis_x": [0.0, 0.0, 0.0], "caxis_y": [0.0, 0.0, 0.0], "caxis_z": [0.0, 0.0, 0.0]}, "base_length": 0, "indices": [0, 0], "position": [0, 0], "texcoord": [0, 0], "texcoord2": [0, 0], "shade_tangs": [0, 0], "normal": [0, 0], "tangent": [0, 0], "group": [0, 0], "color": [0, 0], "vertex_colors": []}, {"boundings": {"bb": {"max_x": 0.41862, "max_y": 0.41862, "max_z": 0.01216, "min_x": -0.41862, "min_y": -0.41862, "min_z": 0.00277}, "be_ax": [0.73514, 0.72, 0.00808], "be_cen": [-0.00016, -0.00034, 0.00746], "rbb": {"rbb_c": [-0.00852915458381176, -0.016276421025395393, 0.007463661953806877], "rbb_s": [0.42703235149383545, 0.41823703050613403, 0.004691642709076405]}, "caxis_x": [0.9990948438644409, -0.04253879189491272, 0.0], "caxis_y": [0.04253879189491272, 0.9990948438644409, 0.0], "caxis_z": [0.0, 0.0, 1.0]}, "base_length": 40, "indices": [0, 66], "position": [0, 120], "texcoord": [120, 80], "texcoord2": [0, 0], "shade_tangs": [0, 0], "normal": [0, 120], "tangent": [120, 160], "group": [0, 0], "color": [0, 0], "vertex_colors": []}], "b4w_shape_keys": [], "b4w_boundings": {"bb": {"max_x": 0.41862, "max_y": 0.41862, "max_z": 0.01216, "min_x": -0.41862, "min_y": -0.41862, "min_z": 0.00277}, "be_ax": [0.73514, 0.72, 0.00808], "be_cen": [-0.00016, -0.00034, 0.00746], "bs_rad": 0.52808, "bc_rad": 0.52806, "bs_cen": [-0.07436, 0.00412, 0.00804], "bc_cen": [-0.07435, 0.00412, 0.00746], "bb_src": {"max_x": 0.41862, "max_y": 0.41862, "max_z": 0.01216, "min_x": -0.41862, "min_y": -0.41862, "min_z": 0.00277}, "rbb": {"rbb_c": [-0.00852915458381176, -0.016276421025395393, 0.007463661953806877], "rbb_s": [0.42703235149383545, 0.41823703050613403, 0.004691642709076405]}, "caxis_x": [0.9990948438644409, -0.04253879189491272, 0.0], "caxis_y": [0.04253879189491272, 0.9990948438644409, 0.0], "caxis_z": [0.0, 0.0, 1.0]}}, {"name": "Mesh", "uuid": "3d6214a8b825ed4d0e4847903deb5dca", "materials": [{"uuid": "693050a9303c88ff2328f1150d1afc0c"}], "b4w_vertex_anim": [], "vertex_groups": [], "uv_textures": [], "active_vcol_name": null, "submeshes": [{"boundings": {"bb": {"max_x": 9.536, "max_y": 0.691, "max_z": 0.0461, "min_x": 0.017, "min_y": -0.009, "min_z": -0.0461}, "be_ax": [8.24092, 0.61919, 0.07981], "be_cen": [4.78433, 0.34111, 0], "rbb": {"rbb_c": [4.776500225067139, 0.34114038944244385, 0.0], "rbb_s": [4.760219573974609, 0.35766246914863586, 0.04610000178217888]}, "caxis_x": [0.9999976754188538, -0.002142972080036998, 0.0], "caxis_y": [0.002142972080036998, 0.9999976754188538, 0.0], "caxis_z": [0.0, 0.0, 1.0]}, "base_length": 2664, "indices": [66, 7692], "position": [200, 7992], "texcoord": [0, 0], "texcoord2": [0, 0], "shade_tangs": [0, 0], "normal": [280, 7992], "tangent": [0, 0], "group": [0, 0], "color": [0, 0], "vertex_colors": []}], "b4w_shape_keys": [], "b4w_boundings": {"bb": {"max_x": 9.536, "max_y": 0.691, "max_z": 0.0461, "min_x": 0.017, "min_y": -0.009, "min_z": -0.0461}, "be_ax": [8.24092, 0.61919, 0.07981], "be_cen": [4.78433, 0.34111, 0], "bs_rad": 4.77192, "bc_rad": 4.7717, "bs_cen": [4.77656, 0.34182, 0.00012], "bc_cen": [4.77656, 0.34181, 0], "bb_src": {"max_x": 9.536, "max_y": 0.691, "max_z": 0.0461, "min_x": 0.017, "min_y": -0.009, "min_z": -0.0461}, "rbb": {"rbb_c": [4.776500225067139, 0.34114038944244385, 0.0], "rbb_s": [4.760219573974609, 0.35766246914863586, 0.04610000178217888]}, "caxis_x": [0.9999976754188538, -0.002142972080036998, 0.0], "caxis_y": [0.002142972080036998, 0.9999976754188538, 0.0], "caxis_z": [0.0, 0.0, 1.0]}}, {"name": "Cube.001_MODIFIERS_APPLIED", "uuid": "aa0c8face5ecc9442e5f8934091e5c40", "materials": [{"uuid": "764864695a36734c3b2f0e9f337bfa20"}, {"uuid": "28040b64f558e7f6adc9fff373575f54"}], "b4w_vertex_anim": [], "vertex_groups": [], "uv_textures": ["UVMap"], "active_vcol_name": "Col", "submeshes": [{"boundings": {"bb": {"max_x": 0, "max_y": 0, "max_z": 0, "min_x": 0, "min_y": 0, "min_z": 0}, "be_ax": [0, 0, 0], "be_cen": [0, 0, 0], "rbb": {"rbb_c": [0.0, 0.0, 0.0], "rbb_s": [0.0, 0.0, 0.0]}, "caxis_x": [0.0, 0.0, 0.0], "caxis_y": [0.0, 0.0, 0.0], "caxis_z": [0.0, 0.0, 0.0]}, "base_length": 0, "indices": [0, 0], "position": [0, 0], "texcoord": [0, 0], "texcoord2": [0, 0], "shade_tangs": [0, 0], "normal": [0, 0], "tangent": [0, 0], "group": [0, 0], "color": [0, 0], "vertex_colors": []}, {"boundings": {"bb": {"max_x": 0.41862, "max_y": 0.41862, "max_z": 0.01216, "min_x": -0.41862, "min_y": -0.41862, "min_z": 0.00277}, "be_ax": [0.73514, 0.72, 0.00808], "be_cen": [-0.00016, -0.00034, 0.00746], "rbb": {"rbb_c": [-0.00852915458381176, -0.016276421025395393, 0.007463661953806877], "rbb_s": [0.42703235149383545, 0.41823703050613403, 0.004691642709076405]}, "caxis_x": [0.9990948438644409, -0.04253879189491272, 0.0], "caxis_y": [0.04253879189491272, 0.9990948438644409, 0.0], "caxis_z": [0.0, 0.0, 1.0]}, "base_length": 40, "indices": [7758, 66], "position": [8192, 120], "texcoord": [8312, 80], "texcoord2": [0, 0], "shade_tangs": [0, 0], "normal": [8272, 120], "tangent": [8392, 160], "group": [0, 0], "color": [0, 0], "vertex_colors": []}], "b4w_shape_keys": [], "b4w_boundings": {"bb": {"max_x": 0.41862, "max_y": 0.41862, "max_z": 0.01216, "min_x": -0.41862, "min_y": -0.41862, "min_z": 0.00277}, "be_ax": [0.73514, 0.72, 0.00808], "be_cen": [-0.00016, -0.00034, 0.00746], "bs_rad": 0.52808, "bc_rad": 0.52806, "bs_cen": [-0.07436, 0.00412, 0.00804], "bc_cen": [-0.07435, 0.00412, 0.00746], "bb_src": {"max_x": 0.41862, "max_y": 0.41862, "max_z": 0.01216, "min_x": -0.41862, "min_y": -0.41862, "min_z": 0.00277}, "rbb": {"rbb_c": [-0.00852915458381176, -0.016276421025395393, 0.007463661953806877], "rbb_s": [0.42703235149383545, 0.41823703050613403, 0.004691642709076405]}, "caxis_x": [0.9990948438644409, -0.04253879189491272, 0.0], "caxis_y": [0.04253879189491272, 0.9990948438644409, 0.0], "caxis_z": [0.0, 0.0, 1.0]}}, {"name": "Plane", "uuid": "d28d5addbadfe558e1da6e2418647ac4", "materials": [{"uuid": "e24cefb9809b42dd5a871719f7b6acf6"}], "b4w_vertex_anim": [], "vertex_groups": [], "uv_textures": [], "active_vcol_name": null, "submeshes": [{"boundings": {"bb": {"max_x": 4, "max_y": 4, "max_z": 0, "min_x": -4, "min_y": -4, "min_z": 0}, "be_ax": [5.65685, 5.65685, 0], "be_cen": [0, 0, 0], "rbb": {"rbb_c": [0.0, 0.0, 0.0], "rbb_s": [4.0, 4.0, 0.0]}, "caxis_x": [1.0, 0.0, 0.0], "caxis_y": [0.0, 1.0, 0.0], "caxis_z": [0.0, 0.0, 1.0]}, "base_length": 4, "indices": [7824, 6], "position": [8392, 12], "texcoord": [0, 0], "texcoord2": [0, 0], "shade_tangs": [0, 0], "normal": [8552, 12], "tangent": [0, 0], "group": [0, 0], "color": [0, 0], "vertex_colors": []}], "b4w_shape_keys": [], "b4w_boundings": {"bb": {"max_x": 4, "max_y": 4, "max_z": 0, "min_x": -4, "min_y": -4, "min_z": 0}, "be_ax": [5.65685, 5.65685, 0], "be_cen": [0, 0, 0], "bs_rad": 5.95699, "bc_rad": 5.95699, "bs_cen": [0.0825, -0.33808, 0], "bc_cen": [0.0825, -0.33808, 0], "bb_src": {"max_x": 4, "max_y": 4, "max_z": 0, "min_x": -4, "min_y": -4, "min_z": 0}, "rbb": {"rbb_c": [0.0, 0.0, 0.0], "rbb_s": [4.0, 4.0, 0.0]}, "caxis_x": [1.0, 0.0, 0.0], "caxis_y": [0.0, 1.0, 0.0], "caxis_z": [0.0, 0.0, 1.0]}}], "armatures": [], "cameras": [{"name": "Camera", "uuid": "0a67d390677dc5f5d5d0b5f4920aea44", "type": "PERSP", "angle": 0.50338, "angle_y": 0.50338, "ortho_scale": 7.314, "clip_start": 0.1, "clip_end": 100, "dof_distance": 0, "b4w_dof_front_start": 1, "b4w_dof_front_end": 5, "b4w_dof_rear_start": 1, "b4w_dof_rear_end": 5, "b4w_dof_power": 2, "b4w_dof_bokeh": false, "b4w_dof_bokeh_intensity": 0.3, "b4w_dof_foreground_blur": false, "b4w_move_style": "TARGET", "b4w_hover_zero_level": 0.0, "b4w_trans_velocity": 1, "b4w_rot_velocity": 1, "b4w_zoom_velocity": 0.1, "b4w_use_target_distance_limits": false, "b4w_distance_min": 1, "b4w_distance_max": 10, "b4w_use_horizontal_clamping": false, "b4w_rotation_left_limit": -0.7853981852531433, "b4w_rotation_right_limit": 0.7853981852531433, "b4w_horizontal_clamping_type": "LOCAL", "b4w_use_vertical_clamping": false, "b4w_rotation_down_limit": -0.7853981852531433, "b4w_rotation_up_limit": 0.7853981852531433, "b4w_vertical_clamping_type": "LOCAL", "b4w_horizontal_translation_min": -10, "b4w_horizontal_translation_max": 10, "b4w_vertical_translation_min": -10, "b4w_vertical_translation_max": 10, "b4w_use_zooming": false, "b4w_hover_angle_min": 0.0, "b4w_hover_angle_max": 1.5707963705062866, "b4w_enable_hover_hor_rotation": true, "b4w_use_panning": true, "b4w_use_pivot_limits": false, "b4w_pivot_z_min": 0.0, "b4w_pivot_z_max": 10.0, "b4w_target": [0, 0, 0], "dof_object": null}], "curves": [], "lamps": [{"animation_data": null, "name": "Lamp.003", "uuid": "c0693f463231c2e2e44e33d6f8f2abfa", "type": "SUN", "energy": 1, "distance": 30, "use_diffuse": true, "use_specular": true, "falloff_type": null, "clip_start": 0.1, "clip_end": 30.0, "spot_size": null, "spot_blend": null, "b4w_generate_shadows": true, "b4w_dynamic_intensity": false, "color": [1, 1, 1]}], "sounds": [], "speakers": [], "particles": [{"name": "ParticleSettings.001", "uuid": "9513ee3d5c74c6f90374317176b9d753", "type": "EMITTER", "count": 5, "emit_from": "FACE", "frame_start": 1, "frame_end": 200, "lifetime": 400, "lifetime_random": 0, "normal_factor": 0.3, "factor_random": 0, "use_rotations": true, "angular_velocity_mode": "VELOCITY", "angular_velocity_factor": 0, "particle_size": 0.2, "mass": 1, "brownian_factor": 0, "material": 1, "use_render_emitter": true, "render_type": "BILLBOARD", "use_whole_group": false, "effector_weights": {"gravity": 0, "wind": 1}, "b4w_cyclic": true, "b4w_fade_in": 0, "b4w_fade_out": 0, "b4w_randomize_emission": false, "b4w_allow_nla": true, "b4w_initial_rand_rotation": false, "use_rotation_dupli": false, "b4w_rotation_type": "Z", "b4w_rand_rotation_strength": 1, "b4w_hair_billboard": false, "b4w_hair_billboard_type": "BASIC", "b4w_hair_billboard_jitter_amp": 0, "b4w_hair_billboard_jitter_freq": 0, "b4w_hair_billboard_geometry": "SPHERICAL", "b4w_dynamic_grass": false, "b4w_dynamic_grass_scale_threshold": 0.009999999776482582, "b4w_wind_bend_inheritance": "PARENT", "b4w_shadow_inheritance": "PARENT", "b4w_reflection_inheritance": "PARENT", "b4w_vcol_from_name": "", "b4w_vcol_to_name": "", "b4w_billboard_align": "VIEW", "billboard_tilt": -1.0, "billboard_tilt_random": 0.0, "b4w_coordinate_system": "LOCAL", "b4w_enable_soft_particles": true, "b4w_particles_softness": 0.25, "texture_slots": [{"use_map_size": true, "texture": {"uuid": "257c8e7ed183b18ab2676c3bdbeb9a9a"}}], "dupli_object": null, "dupli_weights": [], "dupli_group": null, "use_group_pick_random": null, "use_group_count": null}, {"name": "ParticleSettings", "uuid": "3c55c4a78e0c79d51f4a215f0bd680c1", "type": "EMITTER", "count": 5, "emit_from": "FACE", "frame_start": 1, "frame_end": 200, "lifetime": 400, "lifetime_random": 0, "normal_factor": 0.3, "factor_random": 0, "use_rotations": true, "angular_velocity_mode": "VELOCITY", "angular_velocity_factor": 0, "particle_size": 0.2, "mass": 1, "brownian_factor": 0, "material": 1, "use_render_emitter": true, "render_type": "BILLBOARD", "use_whole_group": false, "effector_weights": {"gravity": 0, "wind": 1}, "b4w_cyclic": true, "b4w_fade_in": 0, "b4w_fade_out": 0, "b4w_randomize_emission": false, "b4w_allow_nla": true, "b4w_initial_rand_rotation": false, "use_rotation_dupli": false, "b4w_rotation_type": "Z", "b4w_rand_rotation_strength": 1, "b4w_hair_billboard": false, "b4w_hair_billboard_type": "BASIC", "b4w_hair_billboard_jitter_amp": 0, "b4w_hair_billboard_jitter_freq": 0, "b4w_hair_billboard_geometry": "SPHERICAL", "b4w_dynamic_grass": false, "b4w_dynamic_grass_scale_threshold": 0.009999999776482582, "b4w_wind_bend_inheritance": "PARENT", "b4w_shadow_inheritance": "PARENT", "b4w_reflection_inheritance": "PARENT", "b4w_vcol_from_name": "", "b4w_vcol_to_name": "", "b4w_billboard_align": "VIEW", "billboard_tilt": 1.0, "billboard_tilt_random": 1.0, "b4w_coordinate_system": "LOCAL", "b4w_enable_soft_particles": true, "b4w_particles_softness": 0.25, "texture_slots": [{"use_map_size": true, "texture": {"uuid": "257c8e7ed183b18ab2676c3bdbeb9a9a"}}], "dupli_object": null, "dupli_weights": [], "dupli_group": null, "use_group_pick_random": null, "use_group_count": null}], "objects": [{"name": "Cube.000", "uuid": "99f2111eb8cceafdeadb1b9db3758754", "type": "MESH", "body_text": null, "data": {"uuid": "fea8b50337660af2f9e5c1f224794f91"}, "proxy": null, "dupli_group": null, "parent": null, "b4w_viewport_alignment": null, "pinverse_tsr": null, "parent_type": "OBJECT", "parent_bone": "", "b4w_cluster_data": {"cluster_id": -1}, "modifiers": [], "constraints": [], "particle_systems": [{"name": "ParticleSystem", "seed": 0, "transforms": [0, 0], "settings": {"uuid": "9513ee3d5c74c6f90374317176b9d753"}}], "animation_data": null, "b4w_do_not_batch": false, "b4w_dynamic_geometry": false, "b4w_do_not_cull": false, "b4w_disable_fogging": false, "b4w_do_not_render": false, "b4w_hidden_on_load": false, "b4w_shadow_cast": false, "b4w_shadow_receive": false, "b4w_reflexible": true, "b4w_reflexible_only": false, "b4w_reflective": false, "b4w_reflection_type": "PLANE", "b4w_caustics": false, "b4w_wind_bending": false, "b4w_wind_bending_angle": 10, "b4w_wind_bending_freq": 0.25, "b4w_detail_bending_amp": 0.1, "b4w_detail_bending_freq": 1, "b4w_branch_bending_amp": 0.3, "b4w_main_bend_stiffness_col": "", "b4w_detail_bend_colors": {"leaves_stiffness_col": "", "leaves_phase_col": "", "overall_stiffness_col": ""}, "b4w_lod_transition": 0.01, "lod_levels": [], "b4w_proxy_inherit_anim": true, "b4w_selectable": false, "b4w_outlining": false, "b4w_billboard": false, "b4w_pres_glob_orientation": false, "b4w_billboard_geometry": "SPHERICAL", "b4w_outline_settings": {"outline_duration": 1, "outline_period": 1, "outline_relapses": 0}, "b4w_outline_on_select": false, "b4w_use_default_animation": true, "b4w_anim_behavior": "CYCLIC", "b4w_animation_mixing": false, "b4w_shadow_cast_only": false, "b4w_collision": false, "b4w_collision_id": "", "b4w_vehicle": false, "b4w_vehicle_settings": null, "b4w_character": false, "b4w_character_settings": null, "b4w_floating": false, "b4w_floating_settings": null, "pose": null, "field": null, "b4w_correct_bounding_offset": "AUTO", "game": {"physics_type": "STATIC", "use_ghost": false, "use_sleep": false, "mass": 1, "velocity_min": 0, "velocity_max": 0, "damping": 0.04, "rotation_damping": 0.1, "lock_location_x": false, "lock_location_y": false, "lock_location_z": false, "lock_rotation_x": false, "lock_rotation_y": false, "lock_rotation_z": false, "collision_margin": 0.03999999910593033, "collision_group": 1, "collision_mask": 65535, "use_collision_bounds": false, "collision_bounds_type": "BOX", "use_collision_compound": false}, "location": [0, 0.90764, 0], "rotation_quaternion": [1, 0, 0, 0], "scale": [1, 1, 1], "b4w_object_tags": null, "b4w_anchor": null}, {"name": "Text", "uuid": "3e8bac43b28f45f8d4f2d7e579a67c2a", "type": "MESH", "body_text": "Tilt: OFF         Tilt: ON", "data": {"uuid": "3d6214a8b825ed4d0e4847903deb5dca"}, "proxy": null, "dupli_group": null, "parent": null, "b4w_viewport_alignment": null, "pinverse_tsr": null, "parent_type": "OBJECT", "parent_bone": "", "b4w_cluster_data": {"cluster_id": -1}, "modifiers": [], "constraints": [], "particle_systems": [], "animation_data": null, "b4w_do_not_batch": false, "b4w_dynamic_geometry": false, "b4w_do_not_cull": false, "b4w_disable_fogging": false, "b4w_do_not_render": false, "b4w_hidden_on_load": false, "b4w_shadow_cast": false, "b4w_shadow_receive": false, "b4w_reflexible": false, "b4w_reflexible_only": false, "b4w_reflective": false, "b4w_reflection_type": "PLANE", "b4w_caustics": false, "b4w_wind_bending": false, "b4w_wind_bending_angle": 10, "b4w_wind_bending_freq": 0.25, "b4w_detail_bending_amp": 0.1, "b4w_detail_bending_freq": 1, "b4w_branch_bending_amp": 0.3, "b4w_main_bend_stiffness_col": "", "b4w_detail_bend_colors": {"leaves_stiffness_col": "", "leaves_phase_col": "", "overall_stiffness_col": ""}, "b4w_lod_transition": 0.01, "lod_levels": [], "b4w_proxy_inherit_anim": true, "b4w_selectable": false, "b4w_outlining": false, "b4w_billboard": false, "b4w_pres_glob_orientation": false, "b4w_billboard_geometry": "SPHERICAL", "b4w_outline_settings": {"outline_duration": 1, "outline_period": 1, "outline_relapses": 0}, "b4w_outline_on_select": false, "b4w_use_default_animation": false, "b4w_anim_behavior": "CYCLIC", "b4w_animation_mixing": false, "b4w_shadow_cast_only": false, "b4w_collision": false, "b4w_collision_id": "", "b4w_vehicle": false, "b4w_vehicle_settings": null, "b4w_character": false, "b4w_character_settings": null, "b4w_floating": false, "b4w_floating_settings": null, "pose": null, "field": null, "b4w_correct_bounding_offset": "AUTO", "game": {"physics_type": "NO_COLLISION", "use_ghost": false, "use_sleep": false, "mass": 1, "velocity_min": 0, "velocity_max": 0, "damping": 0.04, "rotation_damping": 0.1, "lock_location_x": false, "lock_location_y": false, "lock_location_z": false, "lock_rotation_x": false, "lock_rotation_y": false, "lock_rotation_z": false, "collision_margin": 0.03999999910593033, "collision_group": 1, "collision_mask": 65535, "use_collision_bounds": false, "collision_bounds_type": "BOX", "use_collision_compound": false}, "location": [-0.87725, 1.30997, 0.01656], "rotation_quaternion": [0.70711, 0, 0, -0.70711], "scale": [0.23336, 0.23336, 0.23336], "b4w_object_tags": null, "b4w_anchor": null}, {"name": "Cube.001", "uuid": "5647cc3ba61d45ce9fea69421cddbd0e", "type": "MESH", "body_text": null, "data": {"uuid": "aa0c8face5ecc9442e5f8934091e5c40"}, "proxy": null, "dupli_group": null, "parent": null, "b4w_viewport_alignment": null, "pinverse_tsr": null, "parent_type": "OBJECT", "parent_bone": "", "b4w_cluster_data": {"cluster_id": -1}, "modifiers": [], "constraints": [], "particle_systems": [{"name": "ParticleSystem", "seed": 0, "transforms": [0, 0], "settings": {"uuid": "3c55c4a78e0c79d51f4a215f0bd680c1"}}], "animation_data": null, "b4w_do_not_batch": false, "b4w_dynamic_geometry": false, "b4w_do_not_cull": false, "b4w_disable_fogging": false, "b4w_do_not_render": false, "b4w_hidden_on_load": false, "b4w_shadow_cast": false, "b4w_shadow_receive": false, "b4w_reflexible": true, "b4w_reflexible_only": false, "b4w_reflective": false, "b4w_reflection_type": "PLANE", "b4w_caustics": false, "b4w_wind_bending": false, "b4w_wind_bending_angle": 10, "b4w_wind_bending_freq": 0.25, "b4w_detail_bending_amp": 0.1, "b4w_detail_bending_freq": 1, "b4w_branch_bending_amp": 0.3, "b4w_main_bend_stiffness_col": "", "b4w_detail_bend_colors": {"leaves_stiffness_col": "", "leaves_phase_col": "", "overall_stiffness_col": ""}, "b4w_lod_transition": 0.01, "lod_levels": [], "b4w_proxy_inherit_anim": true, "b4w_selectable": false, "b4w_outlining": false, "b4w_billboard": false, "b4w_pres_glob_orientation": false, "b4w_billboard_geometry": "SPHERICAL", "b4w_outline_settings": {"outline_duration": 1, "outline_period": 1, "outline_relapses": 0}, "b4w_outline_on_select": false, "b4w_use_default_animation": true, "b4w_anim_behavior": "CYCLIC", "b4w_animation_mixing": false, "b4w_shadow_cast_only": false, "b4w_collision": false, "b4w_collision_id": "", "b4w_vehicle": false, "b4w_vehicle_settings": null, "b4w_character": false, "b4w_character_settings": null, "b4w_floating": false, "b4w_floating_settings": null, "pose": null, "field": null, "b4w_correct_bounding_offset": "AUTO", "game": {"physics_type": "STATIC", "use_ghost": false, "use_sleep": false, "mass": 1, "velocity_min": 0, "velocity_max": 0, "damping": 0.04, "rotation_damping": 0.1, "lock_location_x": false, "lock_location_y": false, "lock_location_z": false, "lock_rotation_x": false, "lock_rotation_y": false, "lock_rotation_z": false, "collision_margin": 0.03999999910593033, "collision_group": 1, "collision_mask": 65535, "use_collision_bounds": false, "collision_bounds_type": "BOX", "use_collision_compound": false}, "location": [0, -0.55153, 0], "rotation_quaternion": [1, 0, 0, 0], "scale": [1, 1, 1], "b4w_object_tags": null, "b4w_anchor": null}, {"name": "Plane", "uuid": "e017636a5c93a32467f81a772e290395", "type": "MESH", "body_text": null, "data": {"uuid": "d28d5addbadfe558e1da6e2418647ac4"}, "proxy": null, "dupli_group": null, "parent": null, "b4w_viewport_alignment": null, "pinverse_tsr": null, "parent_type": "OBJECT", "parent_bone": "", "b4w_cluster_data": {"cluster_id": -1}, "modifiers": [], "constraints": [], "particle_systems": [], "animation_data": null, "b4w_do_not_batch": false, "b4w_dynamic_geometry": false, "b4w_do_not_cull": false, "b4w_disable_fogging": false, "b4w_do_not_render": false, "b4w_hidden_on_load": false, "b4w_shadow_cast": false, "b4w_shadow_receive": false, "b4w_reflexible": false, "b4w_reflexible_only": false, "b4w_reflective": false, "b4w_reflection_type": "PLANE", "b4w_caustics": false, "b4w_wind_bending": false, "b4w_wind_bending_angle": 10, "b4w_wind_bending_freq": 0.25, "b4w_detail_bending_amp": 0.1, "b4w_detail_bending_freq": 1, "b4w_branch_bending_amp": 0.3, "b4w_main_bend_stiffness_col": "", "b4w_detail_bend_colors": {"leaves_stiffness_col": "", "leaves_phase_col": "", "overall_stiffness_col": ""}, "b4w_lod_transition": 0.01, "lod_levels": [], "b4w_proxy_inherit_anim": true, "b4w_selectable": false, "b4w_outlining": false, "b4w_billboard": false, "b4w_pres_glob_orientation": false, "b4w_billboard_geometry": "SPHERICAL", "b4w_outline_settings": {"outline_duration": 1, "outline_period": 1, "outline_relapses": 0}, "b4w_outline_on_select": false, "b4w_use_default_animation": false, "b4w_anim_behavior": "CYCLIC", "b4w_animation_mixing": false, "b4w_shadow_cast_only": false, "b4w_collision": false, "b4w_collision_id": "", "b4w_vehicle": false, "b4w_vehicle_settings": null, "b4w_character": false, "b4w_character_settings": null, "b4w_floating": false, "b4w_floating_settings": null, "pose": null, "field": null, "b4w_correct_bounding_offset": "AUTO", "game": {"physics_type": "STATIC", "use_ghost": false, "use_sleep": false, "mass": 1, "velocity_min": 0, "velocity_max": 0, "damping": 0.04, "rotation_damping": 0.1, "lock_location_x": false, "lock_location_y": false, "lock_location_z": false, "lock_rotation_x": false, "lock_rotation_y": false, "lock_rotation_z": false, "collision_margin": 0.03999999910593033, "collision_group": 1, "collision_mask": 65535, "use_collision_bounds": false, "collision_bounds_type": "BOX", "use_collision_compound": false}, "location": [0, 0, 0], "rotation_quaternion": [1, 0, 0, 0], "scale": [1, 1, 1], "b4w_object_tags": null, "b4w_anchor": null}, {"name": "Lamp.001", "uuid": "d7d407c5e2164624e1abaaaff0bfee02", "type": "LAMP", "body_text": null, "data": {"uuid": "c0693f463231c2e2e44e33d6f8f2abfa"}, "proxy": null, "dupli_group": null, "parent": null, "b4w_viewport_alignment": null, "pinverse_tsr": null, "parent_type": "OBJECT", "parent_bone": "", "b4w_cluster_data": {"cluster_id": -1}, "modifiers": [], "constraints": [], "particle_systems": [], "animation_data": null, "b4w_do_not_batch": false, "b4w_dynamic_geometry": false, "b4w_do_not_cull": false, "b4w_disable_fogging": false, "b4w_do_not_render": false, "b4w_hidden_on_load": false, "b4w_shadow_cast": false, "b4w_shadow_receive": false, "b4w_reflexible": false, "b4w_reflexible_only": false, "b4w_reflective": false, "b4w_reflection_type": "PLANE", "b4w_caustics": false, "b4w_wind_bending": false, "b4w_wind_bending_angle": 10, "b4w_wind_bending_freq": 0.25, "b4w_detail_bending_amp": 0.1, "b4w_detail_bending_freq": 1, "b4w_branch_bending_amp": 0.3, "b4w_main_bend_stiffness_col": "", "b4w_detail_bend_colors": {"leaves_stiffness_col": "", "leaves_phase_col": "", "overall_stiffness_col": ""}, "b4w_lod_transition": 0.01, "lod_levels": [], "b4w_proxy_inherit_anim": true, "b4w_selectable": false, "b4w_outlining": false, "b4w_billboard": false, "b4w_pres_glob_orientation": false, "b4w_billboard_geometry": "SPHERICAL", "b4w_outline_settings": {"outline_duration": 1, "outline_period": 1, "outline_relapses": 0}, "b4w_outline_on_select": false, "b4w_use_default_animation": false, "b4w_anim_behavior": "CYCLIC", "b4w_animation_mixing": false, "b4w_shadow_cast_only": false, "b4w_collision": false, "b4w_collision_id": "", "b4w_vehicle": false, "b4w_vehicle_settings": null, "b4w_character": false, "b4w_character_settings": null, "b4w_floating": false, "b4w_floating_settings": null, "pose": null, "field": null, "b4w_correct_bounding_offset": "AUTO", "game": {"physics_type": "STATIC", "use_ghost": false, "use_sleep": false, "mass": 1, "velocity_min": 0, "velocity_max": 0, "damping": 0.025, "rotation_damping": 0.159, "lock_location_x": false, "lock_location_y": false, "lock_location_z": false, "lock_rotation_x": false, "lock_rotation_y": false, "lock_rotation_z": false, "collision_margin": 0.05999999865889549, "collision_group": 1, "collision_mask": 255, "use_collision_bounds": false, "collision_bounds_type": "BOX", "use_collision_compound": false}, "location": [3.145, 4.15683, 2.56017], "rotation_quaternion": [0.5344, 0.0947, 0.30677, 0.78189], "scale": [1, 1, 1], "b4w_object_tags": null, "b4w_anchor": null}, {"name": "Camera", "uuid": "aef6e6f243598a21aca3b7276c327eab", "type": "CAMERA", "body_text": null, "data": {"uuid": "0a67d390677dc5f5d5d0b5f4920aea44"}, "proxy": null, "dupli_group": null, "parent": null, "b4w_viewport_alignment": null, "pinverse_tsr": null, "parent_type": "OBJECT", "parent_bone": "", "b4w_cluster_data": {"cluster_id": -1}, "modifiers": [], "constraints": [], "particle_systems": [], "animation_data": null, "b4w_do_not_batch": false, "b4w_dynamic_geometry": false, "b4w_do_not_cull": false, "b4w_disable_fogging": false, "b4w_do_not_render": false, "b4w_hidden_on_load": false, "b4w_shadow_cast": false, "b4w_shadow_receive": false, "b4w_reflexible": false, "b4w_reflexible_only": false, "b4w_reflective": false, "b4w_reflection_type": "PLANE", "b4w_caustics": false, "b4w_wind_bending": false, "b4w_wind_bending_angle": 10, "b4w_wind_bending_freq": 0.25, "b4w_detail_bending_amp": 0.1, "b4w_detail_bending_freq": 1, "b4w_branch_bending_amp": 0.3, "b4w_main_bend_stiffness_col": "", "b4w_detail_bend_colors": {"leaves_stiffness_col": "", "leaves_phase_col": "", "overall_stiffness_col": ""}, "b4w_lod_transition": 0.01, "lod_levels": [], "b4w_proxy_inherit_anim": true, "b4w_selectable": false, "b4w_outlining": false, "b4w_billboard": false, "b4w_pres_glob_orientation": false, "b4w_billboard_geometry": "SPHERICAL", "b4w_outline_settings": {"outline_duration": 1, "outline_period": 1, "outline_relapses": 0}, "b4w_outline_on_select": false, "b4w_use_default_animation": false, "b4w_anim_behavior": "CYCLIC", "b4w_animation_mixing": false, "b4w_shadow_cast_only": false, "b4w_collision": false, "b4w_collision_id": "", "b4w_vehicle": false, "b4w_vehicle_settings": null, "b4w_character": false, "b4w_character_settings": null, "b4w_floating": false, "b4w_floating_settings": null, "pose": null, "field": null, "b4w_correct_bounding_offset": "AUTO", "game": {"physics_type": "STATIC", "use_ghost": false, "use_sleep": false, "mass": 1, "velocity_min": 0, "velocity_max": 0, "damping": 0.566, "rotation_damping": 0.626, "lock_location_x": false, "lock_location_y": false, "lock_location_z": false, "lock_rotation_x": false, "lock_rotation_y": false, "lock_rotation_z": false, "collision_margin": 0.05999999865889549, "collision_group": 1, "collision_mask": 255, "use_collision_bounds": false, "collision_bounds_type": "BOX", "use_collision_compound": false}, "location": [-3.89118, 0.20593, 3.74313], "rotation_quaternion": [0.64593, 0.28771, -0.28771, -0.64593], "scale": [1, 1, 1], "b4w_object_tags": null, "b4w_anchor": null}], "groups": [], "scenes": [{"name": "Scene", "uuid": "620ea16a6f3daab3f4ecfc72f005063d", "b4w_use_nla": false, "b4w_nla_cyclic": false, "b4w_logic_nodes": [], "b4w_use_logic_editor": false, "b4w_enable_dynamic_compressor": false, "b4w_dynamic_compressor_settings": {"threshold": -24, "knee": 30, "ratio": 12, "attack": 0.003, "release": 0.25}, "b4w_shadow_settings": {"csm_resolution": 2048, "blur_samples": "16x", "soft_shadows": true, "self_shadow_polygon_offset": 1, "self_shadow_normal_offset": 0.01, "b4w_enable_csm": false, "csm_num": 1, "csm_first_cascade_border": 10, "first_cascade_blur_radius": 3, "csm_last_cascade_border": 100, "last_cascade_blur_radius": 1.5, "fade_last_cascade": true, "blend_between_cascades": true}, "b4w_god_rays_settings": {"intensity": 0.7, "max_ray_length": 1, "steps_per_pass": 10}, "b4w_ssao_settings": {"radius_increase": 3, "hemisphere": false, "blur_depth": false, "blur_discard_value": 1, "influence": 0.7, "dist_factor": 0, "samples": 16}, "b4w_color_correction_settings": {"brightness": 0, "contrast": 0, "exposure": 1, "saturation": 1}, "b4w_bloom_settings": {"key": 1, "blur": 4, "edge_lum": 1}, "b4w_motion_blur_settings": {"motion_blur_factor": 0.01, "motion_blur_decay_threshold": 0.01}, "b4w_glow_settings": {"render_glow_over_blend": false, "small_glow_mask_coeff": 2, "large_glow_mask_coeff": 2, "small_glow_mask_width": 2, "large_glow_mask_width": 6}, "b4w_outline_color": [1, 1, 1], "b4w_outline_factor": 1, "b4w_enable_physics": true, "b4w_render_shadows": "AUTO", "b4w_render_reflections": "ON", "b4w_reflection_quality": "MEDIUM", "b4w_render_refractions": "AUTO", "b4w_render_dynamic_grass": "AUTO", "b4w_enable_god_rays": false, "b4w_enable_glow_materials": "AUTO", "b4w_enable_ssao": false, "b4w_batch_grid_size": 0, "b4w_anisotropic_filtering": "OFF", "b4w_enable_bloom": false, "b4w_enable_motion_blur": false, "b4w_enable_color_correction": false, "b4w_antialiasing_quality": "MEDIUM", "b4w_enable_object_selection": "AUTO", "b4w_enable_outlining": "AUTO", "b4w_enable_anchors_visibility": "AUTO", "b4w_tags": null, "objects": [{"uuid": "99f2111eb8cceafdeadb1b9db3758754"}, {"uuid": "3e8bac43b28f45f8d4f2d7e579a67c2a"}, {"uuid": "5647cc3ba61d45ce9fea69421cddbd0e"}, {"uuid": "e017636a5c93a32467f81a772e290395"}, {"uuid": "d7d407c5e2164624e1abaaaff0bfee02"}, {"uuid": "aef6e6f243598a21aca3b7276c327eab"}], "camera": {"uuid": "aef6e6f243598a21aca3b7276c327eab"}, "world": {"uuid": "5bc2f654f7a5eca1dcdf972dff1259ba"}, "frame_start": 1, "frame_end": 250, "timeline_markers": null, "fps": 24, "audio_volume": 1, "audio_doppler_speed": 343.3, "audio_doppler_factor": 1, "audio_distance_model": "INVERSE_CLAMPED"}], "worlds": [{"name": "World", "uuid": "5bc2f654f7a5eca1dcdf972dff1259ba", "texture_slots": [], "horizon_color": [0.1562, 0.1771, 0.2011], "zenith_color": [0.0074, 0.0073, 0.01], "use_sky_paper": false, "use_sky_blend": true, "use_sky_real": true, "b4w_use_default_animation": false, "b4w_anim_behavior": "CYCLIC", "light_settings": {"use_environment_light": false, "environment_energy": 1, "environment_color": "PLAIN"}, "b4w_sky_settings": {"render_sky": true, "reflexible": false, "reflexible_only": false, "procedural_skydome": false, "use_as_environment_lighting": false, "color": [0.087, 0.255, 0.6], "rayleigh_brightness": 3.3, "mie_brightness": 0.1, "spot_brightness": 20, "scatter_strength": 0.2, "rayleigh_strength": 0.2, "mie_strength": 0.006, "rayleigh_collection_power": 0.35, "mie_collection_power": 0.5, "mie_distribution": 0.4}, "fog_settings": {"use_fog": false, "intensity": 0, "depth": 25, "start": 5, "height": 0, "falloff": "QUADRATIC", "use_custom_color": true, "color": [0.5, 0.5, 0.5]}, "animation_data": null}], "node_groups": [], "binaries": [{"binfile": "billboard_tilt.bin", "int": 0, "float": 31320, "short": 64936, "ushort": 82064, "uchar": 82064}], "b4w_export_warnings": [], "b4w_export_errors": []}